Workbook

Sheet metrics
A1: id | B1: Name | C1: AlsoKnownAs | D1: Company | E1: Research | F1: Definition | G1: Data Collection Type | H1: Cardsort Group | I1: Cardsort Group ID | J1: Cardsort Subgroup | K1: Cardsort Subgroup ID | L1: IS_Research | M1: Number of companies | N1: Number of research | O1: value | P1: AI Specific Category | Q1: Outcome Goals | R1: Ease of Collection | S1: Related Metrics
A2: 2 | B2: Adoption Rate | C2: % Adoption of Standards; % Adoption to Golden Standards | D2: 501a; 501b; 501k; 511a; 511b; 511c; 511d; 511e; 511f; 511g; 511h; 511i; 511j; 511k; 511l; 511m; 511n; 511o; 511p | E2: 160; 501; 146; 512 | F2: Relates to engineers’ uptake and sustained use of internal tools, workflows, and platforms, reflecting how effectively these resources integrate into daily workflows and solve critical problems. It serves as a key metric for assessing DevEx success and alignment with productivity goals. | G2: quantitative | H2: Process | I2: =VLOOKUP(H2,cardsort_group_IDs!A:B,2,0) -> 204 | J2: Efficiency | K2: =VLOOKUP(J2,cardsort_subgroup_IDs!A:B,2,0) -> 327 | L2: =IF(E2="-",0,1)+IF(D2="-",0,2) -> 3 | M2: =IF(D2="-",0,LEN(D2)-LEN(SUBSTITUTE(D2,";",""))+1) -> 19 | N2: =IF(E2="-",0,LEN(E2)-LEN(SUBSTITUTE(E2,";",""))+1) -> 4 | O2: =SUM(M2:N2) -> 23 | P2: None | Q2: Developer Experience | R2: Moderate | S2: 140
A3: 4 | B3: Application Startup Duration | C3: - | D3: 201 | E3: - | F3: The time needed to startup an application locally. | G3: quantitative | H3: System | I3: =VLOOKUP(H3,cardsort_group_IDs!A:B,2,0) -> 202 | J3: Build Time | K3: =VLOOKUP(J3,cardsort_subgroup_IDs!A:B,2,0) -> 303 | L3: =IF(E3="-",0,1)+IF(D3="-",0,2) -> 2 | M3: =IF(D3="-",0,LEN(D3)-LEN(SUBSTITUTE(D3,";",""))+1) -> 1 | N3: =IF(E3="-",0,LEN(E3)-LEN(SUBSTITUTE(E3,";",""))+1) -> 0 | O3: =SUM(M3:N3) -> 1 | P3: None | Q3: Developer Experience | R3: Easy | S3: -
A4: 9 | B4: Branch Lifetime | C4: - | D4: 501j; 516c | E4: 501; 183 | F4: The time elapsed between branch creation until merge to main/production. | G4: quantitative | H4: Process | I4: =VLOOKUP(H4,cardsort_group_IDs!A:B,2,0) -> 204 | J4: Cycle Time | K4: =VLOOKUP(J4,cardsort_subgroup_IDs!A:B,2,0) -> 306 | L4: =IF(E4="-",0,1)+IF(D4="-",0,2) -> 3 | M4: =IF(D4="-",0,LEN(D4)-LEN(SUBSTITUTE(D4,";",""))+1) -> 2 | N4: =IF(E4="-",0,LEN(E4)-LEN(SUBSTITUTE(E4,";",""))+1) -> 2 | O4: =SUM(M4:N4) -> 4 | P4: None | Q4: Organizational Effectiveness | R4: Easy | S4: 87
A5: 10 | B5: Burnout Risk Score | C5: - | D5: 501m | E5: 503; 501; 183; 522 | F5: Evaluates developers’ mental health, job fulfillment, and workplace conditions. It serves as a critical indicator of systemic issues that harm productivity and retention. | G5: qualitative | H5: Developer Enablement | I5: =VLOOKUP(H5,cardsort_group_IDs!A:B,2,0) -> 203 | J5: Work Load | K5: =VLOOKUP(J5,cardsort_subgroup_IDs!A:B,2,0) -> 307 | L5: =IF(E5="-",0,1)+IF(D5="-",0,2) -> 3 | M5: =IF(D5="-",0,LEN(D5)-LEN(SUBSTITUTE(D5,";",""))+1) -> 1 | N5: =IF(E5="-",0,LEN(E5)-LEN(SUBSTITUTE(E5,";",""))+1) -> 4 | O5: =SUM(M5:N5) -> 5 | P5: None | Q5: Developer Experience | R5: Moderate | S5: -
A6: 11 | B6: Business Objective Advancement | C6: - | D6: - | E6: 183 | F6: Refers to measuring how effectively software development efforts align with and contribute to achieving specific organizational goals. This metric focuses on outcome-driven impact rather than raw activity metrics (e.g., lines of code, commits). | G6: quantitative | H6: Business | I6: =VLOOKUP(H6,cardsort_group_IDs!A:B,2,0) -> 201 | J6: Optimal Resource Allocation | K6: =VLOOKUP(J6,cardsort_subgroup_IDs!A:B,2,0) -> 302 | L6: =IF(E6="-",0,1)+IF(D6="-",0,2) -> 1 | M6: =IF(D6="-",0,LEN(D6)-LEN(SUBSTITUTE(D6,";",""))+1) -> 0 | N6: =IF(E6="-",0,LEN(E6)-LEN(SUBSTITUTE(E6,";",""))+1) -> 1 | O6: =SUM(M6:N6) -> 1 | P6: None | Q6: Organizational Effectiveness | R6: Complex | S6: -
A7: 12 | B7: Change Failure Rate | C7: Change Fail Rate; Change Fail Percentage | D7: 501c; 131h; 501g; 202a; 511a; 511c; 511d; 511r; 511f; 511g; 511j; 511k; 511m; 511i | E7: 514; 505; 506; 508; 9; 160; 501; 131; 202; 183; 146; 512; 520 | F7: This metric measures the percentage of deployments that cause failures in production, requiring hotfixes or rollbacks. A lower change failure rate indicates a more reliable delivery process. | G7: quantitative | H7: Quality | I7: =VLOOKUP(H7,cardsort_group_IDs!A:B,2,0) -> 205 | J7: Failure Rate | K7: =VLOOKUP(J7,cardsort_subgroup_IDs!A:B,2,0) -> 308 | L7: =IF(E7="-",0,1)+IF(D7="-",0,2) -> 3 | M7: =IF(D7="-",0,LEN(D7)-LEN(SUBSTITUTE(D7,";",""))+1) -> 14 | N7: =IF(E7="-",0,LEN(E7)-LEN(SUBSTITUTE(E7,";",""))+1) -> 13 | O7: =SUM(M7:N7) -> 27 | P7: Impact | Q7: Product Excellence | R7: Easy | S7: 31
A8: 13 | B8: CI Determinism | C8: - | D8: 170 | E8: 521 | F8: The opposite of test flakiness: the chance that a test suite’s result will be valid (not a flake) ensures that identical inputs in a continuous integration (CI) pipeline always produce the same outputs (binaries, artifacts, test results). This guarantees reproducibility, reliability, and traceability in software builds, critical for debugging, compliance, and safety-critical systems. | G8: quantitative | H8: Quality | I8: =VLOOKUP(H8,cardsort_group_IDs!A:B,2,0) -> 205 | J8: Test Coverage | K8: =VLOOKUP(J8,cardsort_subgroup_IDs!A:B,2,0) -> 309 | L8: =IF(E8="-",0,1)+IF(D8="-",0,2) -> 3 | M8: =IF(D8="-",0,LEN(D8)-LEN(SUBSTITUTE(D8,";",""))+1) -> 1 | N8: =IF(E8="-",0,LEN(E8)-LEN(SUBSTITUTE(E8,";",""))+1) -> 1 | O8: =SUM(M8:N8) -> 2 | P8: None | Q8: Product Excellence | R8: Moderate | S8: -
A9: 14 | B9: CI Pipeline Failure Rate | C9: - | D9: 501g; 510 | E9: 501; 521 | F9: Measures the percentage of builds or automated workflows in a continuous integration (CI) system that fail due to errors (e.g., compilation issues, test failures, dependency conflicts). | G9: quantitative | H9: Quality | I9: =VLOOKUP(H9,cardsort_group_IDs!A:B,2,0) -> 205 | J9: Failure Rate | K9: =VLOOKUP(J9,cardsort_subgroup_IDs!A:B,2,0) -> 308 | L9: =IF(E9="-",0,1)+IF(D9="-",0,2) -> 3 | M9: =IF(D9="-",0,LEN(D9)-LEN(SUBSTITUTE(D9,";",""))+1) -> 2 | N9: =IF(E9="-",0,LEN(E9)-LEN(SUBSTITUTE(E9,";",""))+1) -> 2 | O9: =SUM(M9:N9) -> 4 | P9: None | Q9: Product Excellence | R9: Easy | S9: -
A10: 15 | B10: CI Build Time | C10: Post-Commit CI Speed; CI Pipeline P50 Build Time | D10: 501g; 170; 501o | E10: 501; 521 | F10: Refers to the (median or mean) duration of successful builds in a continuous integration (CI) pipeline. Might be quantified for individual or a group of commits. | G10: quantitative | H10: Process | I10: =VLOOKUP(H10,cardsort_group_IDs!A:B,2,0) -> 204 | J10: Cycle Time | K10: =VLOOKUP(J10,cardsort_subgroup_IDs!A:B,2,0) -> 306 | L10: =IF(E10="-",0,1)+IF(D10="-",0,2) -> 3 | M10: =IF(D10="-",0,LEN(D10)-LEN(SUBSTITUTE(D10,";",""))+1) -> 3 | N10: =IF(E10="-",0,LEN(E10)-LEN(SUBSTITUTE(E10,";",""))+1) -> 2 | O10: =SUM(M10:N10) -> 5 | P10: None | Q10: Developer Experience | R10: Easy | S10: -
A11: 16 | B11: Code Churn | C11: - | D11: 501m; 131e | E11: 105; 501; 131 | F11: Is the amount of code rewritten shortly after being written. | G11: quantitative | H11: Quality | I11: =VLOOKUP(H11,cardsort_group_IDs!A:B,2,0) -> 205 | J11: Code Rework | K11: =VLOOKUP(J11,cardsort_subgroup_IDs!A:B,2,0) -> 310 | L11: =IF(E11="-",0,1)+IF(D11="-",0,2) -> 3 | M11: =IF(D11="-",0,LEN(D11)-LEN(SUBSTITUTE(D11,";",""))+1) -> 2 | N11: =IF(E11="-",0,LEN(E11)-LEN(SUBSTITUTE(E11,";",""))+1) -> 3 | O11: =SUM(M11:N11) -> 5 | P11: None | Q11: Product Excellence | R11: Easy | S11: -
A12: 17 | B12: Code Reviewer Response Time | C12: Code Reviewer Response Time (P50 and P90); Diff Response Time | D12: 170; 146b; 131l; 517a; 516c | E12: 506; 131; 146; 183; 146; 521 | F12: Measures how long it takes, in business hours, for code reviewers to respond to each update of the code review from the author. | G12: quantitative | H12: Team | I12: =VLOOKUP(H12,cardsort_group_IDs!A:B,2,0) -> 206 | J12: Review Process | K12: =VLOOKUP(J12,cardsort_subgroup_IDs!A:B,2,0) -> 311 | L12: =IF(E12="-",0,1)+IF(D12="-",0,2) -> 3 | M12: =IF(D12="-",0,LEN(D12)-LEN(SUBSTITUTE(D12,";",""))+1) -> 5 | N12: =IF(E12="-",0,LEN(E12)-LEN(SUBSTITUTE(E12,";",""))+1) -> 6 | O12: =SUM(M12:N12) -> 11 | P12: None | Q12: Organizational Effectiveness | R12: Easy | S12: -
A13: 18 | B13: Code Rework Rate | C13: PR revert rate | D13: 131q; 131r; 511k | E13: 131; 520 | F13: Is the percentage of code changes that modify recently changed code. | G13: quantitative | H13: Quality | I13: =VLOOKUP(H13,cardsort_group_IDs!A:B,2,0) -> 205 | J13: Code Rework | K13: =VLOOKUP(J13,cardsort_subgroup_IDs!A:B,2,0) -> 310 | L13: =IF(E13="-",0,1)+IF(D13="-",0,2) -> 3 | M13: =IF(D13="-",0,LEN(D13)-LEN(SUBSTITUTE(D13,";",""))+1) -> 3 | N13: =IF(E13="-",0,LEN(E13)-LEN(SUBSTITUTE(E13,";",""))+1) -> 2 | O13: =SUM(M13:N13) -> 5 | P13: Impact | Q13: Product Excellence | R13: Easy | S13: -
A14: 19 | B14: Produced Code | C14: KLOC - Lines of Code; Code Owned by Time; Committed Source Lines of Code by Time; Source Lines of Code by Time; Lines Deleted; Lines Inserted; Number of Lines of Code Modified; Engineering Productivity; Commit Count | D14: 501m; 32a; 232a; 511b; 232 | E14: 503; 7; 13; 15; 31; 36; 46; 47; 49; 51; 52; 92; 101; 111; 233; 237; 20; 32; 501; 131 | F14: Tracks contributions to the codebase, for example by number of lines of code. | G14: quantitative | H14: Output | I14: =VLOOKUP(H14,cardsort_group_IDs!A:B,2,0) -> 207 | J14: Produced Output | K14: =VLOOKUP(J14,cardsort_subgroup_IDs!A:B,2,0) -> 312 | L14: =IF(E14="-",0,1)+IF(D14="-",0,2) -> 3 | M14: =IF(D14="-",0,LEN(D14)-LEN(SUBSTITUTE(D14,";",""))+1) -> 5 | N14: =IF(E14="-",0,LEN(E14)-LEN(SUBSTITUTE(E14,";",""))+1) -> 20 | O14: =SUM(M14:N14) -> 25 | P14: None | Q14: Organizational Effectiveness | R14: Easy | S14: -
A15: 20 | B15: Cognitive Load Score | C15: Cognitive Effort | D15: - | E15: 504; 11; 96; 214; 513; 517b; 523 | F15: Self-reported mental effort required to perform tasks. Avoiding multitasking, high WIP (work in progress) counts, and attention splitting to maintain focus and reduce cognitive overhead. | G15: qualitative | H15: Developer Enablement | I15: =VLOOKUP(H15,cardsort_group_IDs!A:B,2,0) -> 203 | J15: Ease of Delivery | K15: =VLOOKUP(J15,cardsort_subgroup_IDs!A:B,2,0) -> 313 | L15: =IF(E15="-",0,1)+IF(D15="-",0,2) -> 1 | M15: =IF(D15="-",0,LEN(D15)-LEN(SUBSTITUTE(D15,";",""))+1) -> 0 | N15: =IF(E15="-",0,LEN(E15)-LEN(SUBSTITUTE(E15,";",""))+1) -> 7 | O15: =SUM(M15:N15) -> 7 | P15: Impact | Q15: Developer Experience | R15: Complex | S15: -
A16: 22 | B16: CI/CD Health Score | C16: - | D16: 501m | E16: 503; 501 | F16: Measures the effectiveness of automated build, test, and deployment processes in enabling rapid, reliable software delivery. | G16: quantitative | H16: Process | I16: =VLOOKUP(H16,cardsort_group_IDs!A:B,2,0) -> 204 | J16: Efficiency | K16: =VLOOKUP(J16,cardsort_subgroup_IDs!A:B,2,0) -> 327 | L16: =IF(E16="-",0,1)+IF(D16="-",0,2) -> 3 | M16: =IF(D16="-",0,LEN(D16)-LEN(SUBSTITUTE(D16,";",""))+1) -> 1 | N16: =IF(E16="-",0,LEN(E16)-LEN(SUBSTITUTE(E16,";",""))+1) -> 2 | O16: =SUM(M16:N16) -> 3 | P16: None | Q16: Organizational Effectiveness | R16: Moderate | S16: -
A17: 23 | B17: Contribution Volume | C17: Number of Modifications / Modules / WorkItems / Requirements | D17: - | E17: 506; 15 | F17: The number of contribution units, such as modifications, modules touched, work items closed, or requirements implemented, by an individual developer or team within a period. Used to spot trends in team capacity, not as a standalone productivity score. | G17: quantitative | H17: Team | I17: =VLOOKUP(H17,cardsort_group_IDs!A:B,2,0) -> 206 | J17: Task Assignment | K17: =VLOOKUP(J17,cardsort_subgroup_IDs!A:B,2,0) -> 316 | L17: =IF(E17="-",0,1)+IF(D17="-",0,2) -> 1 | M17: =IF(D17="-",0,LEN(D17)-LEN(SUBSTITUTE(D17,";",""))+1) -> 0 | N17: =IF(E17="-",0,LEN(E17)-LEN(SUBSTITUTE(E17,";",""))+1) -> 2 | O17: =SUM(M17:N17) -> 2 | P17: None | Q17: Organizational Effectiveness | R17: Moderate | S17: 134
A18: 24 | B18: Cost Savings | C18: - | D18: - | E18: 508 | F18: Relates to strategic reductions in product development and operational expenses achieved through optimized engineering practices, aligning technical efficiency with business profitability. This is measured by tracking how engineering improvements directly lower costs while maintaining quality and delivery speed. | G18: quantitative | H18: Business | I18: =VLOOKUP(H18,cardsort_group_IDs!A:B,2,0) -> 201 | J18: Optimal Resource Allocation | K18: =VLOOKUP(J18,cardsort_subgroup_IDs!A:B,2,0) -> 302 | L18: =IF(E18="-",0,1)+IF(D18="-",0,2) -> 1 | M18: =IF(D18="-",0,LEN(D18)-LEN(SUBSTITUTE(D18,";",""))+1) -> 0 | N18: =IF(E18="-",0,LEN(E18)-LEN(SUBSTITUTE(E18,";",""))+1) -> 1 | O18: =SUM(M18:N18) -> 1 | P18: None | Q18: Organizational Effectiveness | R18: Complex | S18: -
A19: 25 | B19: Customer Satisfaction Score | C19: CSAT; Customer Experience; Customer Satisfaction; Customer Satisfaction Scores; User/customer satisfaction; NPS | D19: - | E19: 506; 508; 183 | F19: Measures how pleased customers are with a product, service, or interaction, typically via surveys. Responses are aggregated into a percentage score representing the proportion of satisfied customers | G19: qualitative | H19: Customer | I19: =VLOOKUP(H19,cardsort_group_IDs!A:B,2,0) -> 208 | J19: Product Quality | K19: =VLOOKUP(J19,cardsort_subgroup_IDs!A:B,2,0) -> 317 | L19: =IF(E19="-",0,1)+IF(D19="-",0,2) -> 1 | M19: =IF(D19="-",0,LEN(D19)-LEN(SUBSTITUTE(D19,";",""))+1) -> 0 | N19: =IF(E19="-",0,LEN(E19)-LEN(SUBSTITUTE(E19,";",""))+1) -> 3 | O19: =SUM(M19:N19) -> 3 | P19: None | Q19: Product Excellence | R19: Moderate | S19: -
A20: 26 | B20: Number of Customer-Reported Defects | C20: - | D20: 131m; 131n | E20: 131 | F20: Bugs reported by customers in production. | G20: quantitative | H20: Customer | I20: =VLOOKUP(H20,cardsort_group_IDs!A:B,2,0) -> 208 | J20: Product Quality | K20: =VLOOKUP(J20,cardsort_subgroup_IDs!A:B,2,0) -> 317 | L20: =IF(E20="-",0,1)+IF(D20="-",0,2) -> 3 | M20: =IF(D20="-",0,LEN(D20)-LEN(SUBSTITUTE(D20,";",""))+1) -> 2 | N20: =IF(E20="-",0,LEN(E20)-LEN(SUBSTITUTE(E20,";",""))+1) -> 1 | O20: =SUM(M20:N20) -> 3 | P20: None | Q20: Product Excellence | R20: Easy | S20: 80; 29; 42; 133
A21: 27 | B21: Cycle Time | C21: Time From Creating a Patch to Patch Release; Time to Value; Time to Merge (TTM); PR Cycle Time | D21: 501m; 131i; 501d; 209; 510; 511b; 511r; 511m; 511h; 511q; 511p; 517a; 516c | E21: 9; 235; 241; 501; 131; 520 | F21: Measures the time from code commit to code running in production. Shows how quickly team can respond to business needs. | G21: quantitative | H21: Process | I21: =VLOOKUP(H21,cardsort_group_IDs!A:B,2,0) -> 204 | J21: Cycle Time | K21: =VLOOKUP(J21,cardsort_subgroup_IDs!A:B,2,0) -> 306 | L21: =IF(E21="-",0,1)+IF(D21="-",0,2) -> 3 | M21: =IF(D21="-",0,LEN(D21)-LEN(SUBSTITUTE(D21,";",""))+1) -> 13 | N21: =IF(E21="-",0,LEN(E21)-LEN(SUBSTITUTE(E21,";",""))+1) -> 6 | O21: =SUM(M21:N21) -> 19 | P21: Impact | Q21: Organizational Effectiveness | R21: Easy | S21: -
A22: 29 | B22: Number of Defects | C22: Defects per Function Point; Defect Density; Weighted Defects | D22: - | E22: 236; 520; 92 | F22: Measures defect density: the number of errors or failures normalized by a size unit (e.g., function points), sometimes severity-weighted, indicating codebase quality independent of project size. | G22: quantitative | H22: Quality | I22: =VLOOKUP(H22,cardsort_group_IDs!A:B,2,0) -> 205 | J22: Failure Rate | K22: =VLOOKUP(J22,cardsort_subgroup_IDs!A:B,2,0) -> 308 | L22: =IF(E22="-",0,1)+IF(D22="-",0,2) -> 1 | M22: =IF(D22="-",0,LEN(D22)-LEN(SUBSTITUTE(D22,";",""))+1) -> 0 | N22: =IF(E22="-",0,LEN(E22)-LEN(SUBSTITUTE(E22,";",""))+1) -> 3 | O22: =SUM(M22:N22) -> 3 | P22: None | Q22: Product Excellence | R22: Easy | S22: -
A23: 30 | B23: Deployment Frequency | C23: - | D23: 146b; 131k; 131b; 202a; 501k; 146a; 209; 511i; 511d | E23: 505; 506; 514; 508; 9; 96; 160; 501; 131; 202; 146; 182 | F23: How often an organization deploys code/builds to a production environment, regardless of whether that change is yet visible to end users. Higher deployment frequency indicates a more agile and responsive delivery process. | G23: quantitative | H23: Customer | I23: =VLOOKUP(H23,cardsort_group_IDs!A:B,2,0) -> 208 | J23: Deployment Frequency | K23: =VLOOKUP(J23,cardsort_subgroup_IDs!A:B,2,0) -> 318 | L23: =IF(E23="-",0,1)+IF(D23="-",0,2) -> 3 | M23: =IF(D23="-",0,LEN(D23)-LEN(SUBSTITUTE(D23,";",""))+1) -> 9 | N23: =IF(E23="-",0,LEN(E23)-LEN(SUBSTITUTE(E23,";",""))+1) -> 12 | O23: =SUM(M23:N23) -> 21 | P23: Impact | Q23: Organizational Effectiveness | R23: Easy | S23: 94; 79
A24: 31 | B24: Deployment Success Rate | C24: Build Success Rate | D24: 170 | E24: 9; 57; 183; 521 | F24: The percentage of deployment (CI/CD) runs that complete successfully. | G24: quantitative | H24: Quality | I24: =VLOOKUP(H24,cardsort_group_IDs!A:B,2,0) -> 205 | J24: Code Quality | K24: =VLOOKUP(J24,cardsort_subgroup_IDs!A:B,2,0) -> 319 | L24: =IF(E24="-",0,1)+IF(D24="-",0,2) -> 3 | M24: =IF(D24="-",0,LEN(D24)-LEN(SUBSTITUTE(D24,";",""))+1) -> 1 | N24: =IF(E24="-",0,LEN(E24)-LEN(SUBSTITUTE(E24,";",""))+1) -> 4 | O24: =SUM(M24:N24) -> 5 | P24: None | Q24: Organizational Effectiveness | R24: Easy | S24: 12
A25: 32 | B25: Number of Deploys per Service | C25: - | D25: 501c | E25: 501 | F25: This metric in software engineering measures how often a specific service or microservice is deployed within a given timeframe. This metric is commonly used in DevOps and microservices architectures to track deployment frequency across different services. | G25: quantitative | H25: Customer | I25: =VLOOKUP(H25,cardsort_group_IDs!A:B,2,0) -> 208 | J25: Deployment Frequency | K25: =VLOOKUP(J25,cardsort_subgroup_IDs!A:B,2,0) -> 318 | L25: =IF(E25="-",0,1)+IF(D25="-",0,2) -> 3 | M25: =IF(D25="-",0,LEN(D25)-LEN(SUBSTITUTE(D25,";",""))+1) -> 1 | N25: =IF(E25="-",0,LEN(E25)-LEN(SUBSTITUTE(E25,";",""))+1) -> 1 | O25: =SUM(M25:N25) -> 2 | P25: None | Q25: Organizational Effectiveness | R25: Easy | S25: -
A26: 33 | B26: Design | C26: - | D26: 501m | E26: 503; 501 | F26: Captures documentation quality, architectural decisions, and prototyping efforts. | G26: qualitative | H26: Process | I26: =VLOOKUP(H26,cardsort_group_IDs!A:B,2,0) -> 204 | J26: Self-Service and Documentation | K26: =VLOOKUP(J26,cardsort_subgroup_IDs!A:B,2,0) -> 320 | L26: =IF(E26="-",0,1)+IF(D26="-",0,2) -> 3 | M26: =IF(D26="-",0,LEN(D26)-LEN(SUBSTITUTE(D26,";",""))+1) -> 1 | N26: =IF(E26="-",0,LEN(E26)-LEN(SUBSTITUTE(E26,";",""))+1) -> 2 | O26: =SUM(M26:N26) -> 3 | P26: None | Q26: Product Excellence | R26: Complex | S26: -
A27: 34 | B27: Local Build Time | C27: Developer Build Time; Build Time; Application/Package Build Duration; Build Time Efficiency | D27: 170; 131c; 131o; 201 | E27: 503; 501 | F27: Measures the time, in seconds, developers spend waiting for their builds to finish locally during development. Impacts developer flow and productivity. Considered e.g. as median (P50) or P90. | G27: quantitative | H27: System | I27: =VLOOKUP(H27,cardsort_group_IDs!A:B,2,0) -> 202 | J27: Build Time | K27: =VLOOKUP(J27,cardsort_subgroup_IDs!A:B,2,0) -> 303 | L27: =IF(E27="-",0,1)+IF(D27="-",0,2) -> 3 | M27: =IF(D27="-",0,LEN(D27)-LEN(SUBSTITUTE(D27,";",""))+1) -> 4 | N27: =IF(E27="-",0,LEN(E27)-LEN(SUBSTITUTE(E27,";",""))+1) -> 2 | O27: =SUM(M27:N27) -> 6 | P27: None | Q27: Developer Experience | R27: Easy | S27: -
A28: 36 | B28: Developer Satisfaction | C28: CSAT; DSAT; NSAT; Satisfaction Score; Developer Sentiment; Developer Satisfaction; Employee satisfaction; Net User Satisfaction; Satisfaction with Engineering System; Platform and Tool Satisfaction; AI tool CSAT | D28: 501l; 501a; 202a; 501m; 501i; 501f; 501h; 170; 501d; 6a; 510; 511a; 511b; 511d; 511f; 511j; 511k; 511l; 511n; 511q; 511c; 511e; 511g; 511h; 511m; 511n; 511r | E28: 514; 506; 503; 43; 96; 202; 235; 5; 6; 160; 501; 131; 183; 146; 512; 520; 522; 523 | F28: Customer satisfaction score for developers. Measures developer and team happiness with regards to development systems. | G28: qualitative | H28: Developer Enablement | I28: =VLOOKUP(H28,cardsort_group_IDs!A:B,2,0) -> 203 | J28: Satisfaction | K28: =VLOOKUP(J28,cardsort_subgroup_IDs!A:B,2,0) -> 322 | L28: =IF(E28="-",0,1)+IF(D28="-",0,2) -> 3 | M28: =IF(D28="-",0,LEN(D28)-LEN(SUBSTITUTE(D28,";",""))+1) -> 27 | N28: =IF(E28="-",0,LEN(E28)-LEN(SUBSTITUTE(E28,";",""))+1) -> 18 | O28: =SUM(M28:N28) -> 45 | P28: Impact | Q28: Developer Experience | R28: Easy | S28: 155; 162
A29: 37 | B29: Velocity Index Benchmark | C29: - | D29: - | E29: 506 | F29: The Developer Velocity Index (DVI) is a survey that measures an enterprise’s technology, working practices, and organizational enablement and benchmarks them against peers. This comparison helps unearth specific areas of opportunity, whether in backlog management, testing, or security and compliance. For example, one company, well known for its technological progress and all-star developers, sought to define standard working practices more thoughtfully for cross-team collaboration after discovering a high amount of dissatisfaction, rework, and inefficiency reported by developers. | G29: qualitative | H29: Business | I29: =VLOOKUP(H29,cardsort_group_IDs!A:B,2,0) -> 201 | J29: Optimal Resource Allocation | K29: =VLOOKUP(J29,cardsort_subgroup_IDs!A:B,2,0) -> 302 | L29: =IF(E29="-",0,1)+IF(D29="-",0,2) -> 1 | M29: =IF(D29="-",0,LEN(D29)-LEN(SUBSTITUTE(D29,";",""))+1) -> 0 | N29: =IF(E29="-",0,LEN(E29)-LEN(SUBSTITUTE(E29,";",""))+1) -> 1 | O29: =SUM(M29:N29) -> 1 | P29: None | Q29: Organizational Effectiveness | R29: Complex | S29: -
A30: 38 | B30: Diff Authoring Time | C30: Diff Authoring Time (DAT); PR Authoring Time; Diffs per Engineer (PRs or MRs); Commits Performed by Time; Time Spent per Task; Implementation Time per User Story; Task Completion Time; Coding Time; Time to Commit per LOC Changed | D30: 131l; 32a; 511b; 511h | E30: 514; 7; 14; 31; 49; 52; 57; 96;108; 192; 234; 32; 131 | F30: Aims to capture all active human developer time spent on a particular diff, split by the different roles involved. This information is made available in a privacy-aware manner. Active human work on a computer tends to be highly sequential, even if such individual sequences can be extremely short. | G30: quantitative | H30: Process | I30: =VLOOKUP(H30,cardsort_group_IDs!A:B,2,0) -> 204 | J30: Cycle Time | K30: =VLOOKUP(J30,cardsort_subgroup_IDs!A:B,2,0) -> 306 | L30: =IF(E30="-",0,1)+IF(D30="-",0,2) -> 3 | M30: =IF(D30="-",0,LEN(D30)-LEN(SUBSTITUTE(D30,";",""))+1) -> 4 | N30: =IF(E30="-",0,LEN(E30)-LEN(SUBSTITUTE(E30,";",""))+1) -> 13 | O30: =SUM(M30:N30) -> 17 | P30: Impact | Q30: Developer Experience | R30: Moderate | S30: -
A31: 39 | B31: Discoverability of Documentation and Expertise | C31: - | D31: 501m | E31: 503; 501 | F31: Refers to how easily developers can locate critical information (e.g., codebase guides, API references) or identify colleagues with specific knowledge. | G31: qualitative | H31: Process | I31: =VLOOKUP(H31,cardsort_group_IDs!A:B,2,0) -> 204 | J31: Self-Service and Documentation | K31: =VLOOKUP(J31,cardsort_subgroup_IDs!A:B,2,0) -> 320 | L31: =IF(E31="-",0,1)+IF(D31="-",0,2) -> 3 | M31: =IF(D31="-",0,LEN(D31)-LEN(SUBSTITUTE(D31,";",""))+1) -> 1 | N31: =IF(E31="-",0,LEN(E31)-LEN(SUBSTITUTE(E31,";",""))+1) -> 2 | O31: =SUM(M31:N31) -> 3 | P31: None | Q31: Developer Experience | R31: Moderate | S31: -
A32: 40 | B32: Ease of Delivery | C32: Ease | D32: 501c; 501l; 501b; 501e; 501g; 501d; 5a | E32: 514; 5; 160; 501; 115; 146; 183; 522 | F32: Refers to how simple, straightforward, and frictionless it is for developers or teams to deliver software, features, or updates through their development processes and tooling. Captures the perceived and actual effort required to move work from development to production. | G32: qualitative | H32: Developer Enablement | I32: =VLOOKUP(H32,cardsort_group_IDs!A:B,2,0) -> 203 | J32: Ease of Delivery | K32: =VLOOKUP(J32,cardsort_subgroup_IDs!A:B,2,0) -> 313 | L32: =IF(E32="-",0,1)+IF(D32="-",0,2) -> 3 | M32: =IF(D32="-",0,LEN(D32)-LEN(SUBSTITUTE(D32,";",""))+1) -> 7 | N32: =IF(E32="-",0,LEN(E32)-LEN(SUBSTITUTE(E32,";",""))+1) -> 8 | O32: =SUM(M32:N32) -> 15 | P32: Impact | Q32: Developer Experience | R32: Moderate | S32: -
A33: 41 | B33: Engineer Engagement | C33: Engagement; Developer Engagement | D33: 501b; 501c; 501e; 501d | E33: 160; 501 | F33: Refers to the emotional commitment, motivation, and involvement that software engineers or developers have toward their work, team, and organization. | G33: qualitative | H33: Developer Enablement | I33: =VLOOKUP(H33,cardsort_group_IDs!A:B,2,0) -> 203 | J33: Impact and Efficacy | K33: =VLOOKUP(J33,cardsort_subgroup_IDs!A:B,2,0) -> 321 | L33: =IF(E33="-",0,1)+IF(D33="-",0,2) -> 3 | M33: =IF(D33="-",0,LEN(D33)-LEN(SUBSTITUTE(D33,";",""))+1) -> 4 | N33: =IF(E33="-",0,LEN(E33)-LEN(SUBSTITUTE(E33,";",""))+1) -> 2 | O33: =SUM(M33:N33) -> 6 | P33: None | Q33: Developer Experience | R33: Moderate | S33: -
A34: 42 | B34: Error Rates | C34: Defect Rate | D34: - | E34: 508; 9; 101 | F34: Quantifies the frequency of user or system mistakes during interactions with a product (e.g., failed API requests, UI slips, or task errors) | G34: quantitative | H34: Quality | I34: =VLOOKUP(H34,cardsort_group_IDs!A:B,2,0) -> 205 | J34: Failure Rate | K34: =VLOOKUP(J34,cardsort_subgroup_IDs!A:B,2,0) -> 308 | L34: =IF(E34="-",0,1)+IF(D34="-",0,2) -> 1 | M34: =IF(D34="-",0,LEN(D34)-LEN(SUBSTITUTE(D34,";",""))+1) -> 0 | N34: =IF(E34="-",0,LEN(E34)-LEN(SUBSTITUTE(E34,";",""))+1) -> 3 | O34: =SUM(M34:N34) -> 3 | P34: None | Q34: Product Excellence | R34: Easy | S34: 26; 29; 70; 133
A35: 43 | B35: Experience of New Members | C35: - | D35: 501m | E35: 503; 501 | F35: Is a combination of satisfaction, well-being and integration indicators to ensure new developers feel supported, included and able to contribute effectively. | G35: qualitative | H35: Developer Enablement | I35: =VLOOKUP(H35,cardsort_group_IDs!A:B,2,0) -> 203 | J35: Onboarding | K35: =VLOOKUP(J35,cardsort_subgroup_IDs!A:B,2,0) -> 323 | L35: =IF(E35="-",0,1)+IF(D35="-",0,2) -> 3 | M35: =IF(D35="-",0,LEN(D35)-LEN(SUBSTITUTE(D35,";",""))+1) -> 1 | N35: =IF(E35="-",0,LEN(E35)-LEN(SUBSTITUTE(E35,";",""))+1) -> 2 | O35: =SUM(M35:N35) -> 3 | P35: None | Q35: Developer Experience | R35: Moderate | S35: -
A36: 44 | B36: Experiment Velocity | C36: A/B Test Throughput | D36: 501i; 511i | E36: 501; 146 | F36: Refers to the speed and efficiency at which the platform conducts and evaluates A/B tests to optimize features, algorithms, and user experiences. | G36: quantitative | H36: System | I36: =VLOOKUP(H36,cardsort_group_IDs!A:B,2,0) -> 202 | J36: Performance | K36: =VLOOKUP(J36,cardsort_subgroup_IDs!A:B,2,0) -> 324 | L36: =IF(E36="-",0,1)+IF(D36="-",0,2) -> 3 | M36: =IF(D36="-",0,LEN(D36)-LEN(SUBSTITUTE(D36,";",""))+1) -> 2 | N36: =IF(E36="-",0,LEN(E36)-LEN(SUBSTITUTE(E36,";",""))+1) -> 2 | O36: =SUM(M36:N36) -> 4 | P36: Impact | Q36: Organizational Effectiveness | R36: Moderate | S36: -
A37: 45 | B37: Failed Deployment Recovery Time | C37: - | D37: - | E37: 514; 505 | F37: This metric measures the time it takes to recover from a failed deployment (e.g. outage or service failure in production). A lower recovery time indicates a more resilient and responsive system. | G37: quantitative | H37: System | I37: =VLOOKUP(H37,cardsort_group_IDs!A:B,2,0) -> 202 | J37: Failure Recovery | K37: =VLOOKUP(J37,cardsort_subgroup_IDs!A:B,2,0) -> 325 | L37: =IF(E37="-",0,1)+IF(D37="-",0,2) -> 1 | M37: =IF(D37="-",0,LEN(D37)-LEN(SUBSTITUTE(D37,";",""))+1) -> 0 | N37: =IF(E37="-",0,LEN(E37)-LEN(SUBSTITUTE(E37,";",""))+1) -> 2 | O37: =SUM(M37:N37) -> 2 | P37: None | Q37: Organizational Effectiveness | R37: Easy | S37: -
A38: 46 | B38: Feedback Latency | C38: Time to Feedback; CI Feedback Time | D38: - | E38: 504; 214 | F38: The average time between a developer action (e.g., code push, PR submission, build trigger) and the developer receiving a response (e.g., CI/test results, build status, review comments). | G38: quantitative | H38: Team | I38: =VLOOKUP(H38,cardsort_group_IDs!A:B,2,0) -> 206 | J38: Collaboration | K38: =VLOOKUP(J38,cardsort_subgroup_IDs!A:B,2,0) -> 326 | L38: =IF(E38="-",0,1)+IF(D38="-",0,2) -> 1 | M38: =IF(D38="-",0,LEN(D38)-LEN(SUBSTITUTE(D38,";",""))+1) -> 0 | N38: =IF(E38="-",0,LEN(E38)-LEN(SUBSTITUTE(E38,";",""))+1) -> 2 | O38: =SUM(M38:N38) -> 2 | P38: Impact | Q38: Developer Experience | R38: Moderate | S38: -
A39: 50 | B39: Focus Time | C39: Flow State; Deep Work; Focused Work; Uninterrupted Time | D39: 501n; 501j; 501b; 203; 6a; 501m; 517a | E39: 504; 214; 6; 501; 183; 503 | F39: The ability to work in focus or flow, i.e. uninterrupted, in meeting-free blocks that allow the developer to concentrate deeply on their work. Often reported as percentage of total time or average time. | G39: both | H39: Developer Enablement | I39: =VLOOKUP(H39,cardsort_group_IDs!A:B,2,0) -> 203 | J39: Focus Work | K39: =VLOOKUP(J39,cardsort_subgroup_IDs!A:B,2,0) -> 305 | L39: =IF(E39="-",0,1)+IF(D39="-",0,2) -> 3 | M39: =IF(D39="-",0,LEN(D39)-LEN(SUBSTITUTE(D39,";",""))+1) -> 7 | N39: =IF(E39="-",0,LEN(E39)-LEN(SUBSTITUTE(E39,";",""))+1) -> 6 | O39: =SUM(M39:N39) -> 13 | P39: None | Q39: Developer Experience | R39: Complex | S39: 59; 157
A40: 56 | B40: Impact | C40: Direct Customer Impact Measures | D40: 501m | E40: 503; 501; 183 | F40: Evaluates the tangible outcomes and value delivered by development efforts. Unlike raw outputs (e.g., lines of code), impact focuses on business results and user-centric effects of software work. Making significant contributions to one’s business unit or area of ownership, ensuring that work has a tangible impact. | G40: quantitative | H40: Developer Enablement | I40: =VLOOKUP(H40,cardsort_group_IDs!A:B,2,0) -> 203 | J40: Impact and Efficacy | K40: =VLOOKUP(J40,cardsort_subgroup_IDs!A:B,2,0) -> 321 | L40: =IF(E40="-",0,1)+IF(D40="-",0,2) -> 3 | M40: =IF(D40="-",0,LEN(D40)-LEN(SUBSTITUTE(D40,";",""))+1) -> 1 | N40: =IF(E40="-",0,LEN(E40)-LEN(SUBSTITUTE(E40,";",""))+1) -> 3 | O40: =SUM(M40:N40) -> 4 | P40: None | Q40: Organizational Effectiveness | R40: Complex | S40: -
A41: 57 | B41: Initiative Progress and ROI | C41: - | D41: - | E41: 514 | F41: Measures the financial impact and advancement of specific developer experience (DevEx) improvement projects, linking technical efforts to business outcomes. It evaluates whether investments in tools, processes, or workflows deliver measurable returns. | G41: quantitative | H41: Business | I41: =VLOOKUP(H41,cardsort_group_IDs!A:B,2,0) -> 201 | J41: Optimal Resource Allocation | K41: =VLOOKUP(J41,cardsort_subgroup_IDs!A:B,2,0) -> 302 | L41: =IF(E41="-",0,1)+IF(D41="-",0,2) -> 1 | M41: =IF(D41="-",0,LEN(D41)-LEN(SUBSTITUTE(D41,";",""))+1) -> 0 | N41: =IF(E41="-",0,LEN(E41)-LEN(SUBSTITUTE(E41,";",""))+1) -> 1 | O41: =SUM(M41:N41) -> 1 | P41: None | Q41: Organizational Effectiveness | R41: Complex | S41: -
A42: 58 | B42: Inner / Outer Loop Time Spent | C42: Time Spent in Value-added Activities; Time Spent in Different Applications/Activities | D42: 511b | E42: 506; 238; 39 | F42: The proportion of a developer's working time spent on inner-loop activities (coding, building, unit testing) vs. outer-loop activities (integration testing, releasing, deployment). Typically collected via self-report survey or time-tracking tools. Software development activities can be arranged in two loops. The inner loop covers activities directly related to creating the product: coding, building, and unit testing. The outer loop covers tasks needed to push code to production: integration testing, releasing, and deployment. Maximizing inner-loop time is desirable — it directly generates value and is what most developers find most engaging. Better tooling and automation for outer-loop activities frees up more time for inner-loop work. | G42: qualitative | H42: Developer Enablement | I42: =VLOOKUP(H42,cardsort_group_IDs!A:B,2,0) -> 203 | J42: Ease of Delivery | K42: =VLOOKUP(J42,cardsort_subgroup_IDs!A:B,2,0) -> 313 | L42: =IF(E42="-",0,1)+IF(D42="-",0,2) -> 3 | M42: =IF(D42="-",0,LEN(D42)-LEN(SUBSTITUTE(D42,";",""))+1) -> 1 | N42: =IF(E42="-",0,LEN(E42)-LEN(SUBSTITUTE(E42,";",""))+1) -> 3 | O42: =SUM(M42:N42) -> 4 | P42: Impact | Q42: Developer Experience | R42: Moderate | S42: 157
A43: 59 | B43: Number of Interruptions | C43: Nature of Interruptions | D43: - | E43: 503; 506; 241; 501 | F43: Measures the number of interruptions. | G43: qualitative | H43: Developer Enablement | I43: =VLOOKUP(H43,cardsort_group_IDs!A:B,2,0) -> 203 | J43: Focus Work | K43: =VLOOKUP(J43,cardsort_subgroup_IDs!A:B,2,0) -> 305 | L43: =IF(E43="-",0,1)+IF(D43="-",0,2) -> 1 | M43: =IF(D43="-",0,LEN(D43)-LEN(SUBSTITUTE(D43,";",""))+1) -> 0 | N43: =IF(E43="-",0,LEN(E43)-LEN(SUBSTITUTE(E43,";",""))+1) -> 4 | O43: =SUM(M43:N43) -> 4 | P43: Impact | Q43: Developer Experience | R43: Complex | S43: 50
A44: 62 | B44: Change Lead Time | C44: Lead time; Lead Time for Changes; Deployment Time; Time from Commit to Deploy | D44: 202a; 511i; 511l; 183a; 501h | E44: 514; 505; 506; 508; 9; 160; 202; 146; 501 | F44: This metric measures the time it takes for a code commit or change to be successfully deployed to production. It reflects the efficiency of your software delivery process to deliver value to customers. | G44: quantitative | H44: Process | I44: =VLOOKUP(H44,cardsort_group_IDs!A:B,2,0) -> 204 | J44: Cycle Time | K44: =VLOOKUP(J44,cardsort_subgroup_IDs!A:B,2,0) -> 306 | L44: =IF(E44="-",0,1)+IF(D44="-",0,2) -> 3 | M44: =IF(D44="-",0,LEN(D44)-LEN(SUBSTITUTE(D44,";",""))+1) -> 5 | N44: =IF(E44="-",0,LEN(E44)-LEN(SUBSTITUTE(E44,";",""))+1) -> 9 | O44: =SUM(M44:N44) -> 14 | P44: None | Q44: Organizational Effectiveness | R44: Easy | S44: -
A45: 63 | B45: Line Coverage | C45: Code Coverage | D45: 202a; 511i | E45: 9; 202 | F45: Line Coverage is a code coverage metric that measures the percentage of lines in a codebase that have been executed during testing. It helps determine how well a test suite exercises the code. | G45: quantitative | H45: Quality | I45: =VLOOKUP(H45,cardsort_group_IDs!A:B,2,0) -> 205 | J45: Test Coverage | K45: =VLOOKUP(J45,cardsort_subgroup_IDs!A:B,2,0) -> 309 | L45: =IF(E45="-",0,1)+IF(D45="-",0,2) -> 3 | M45: =IF(D45="-",0,LEN(D45)-LEN(SUBSTITUTE(D45,";",""))+1) -> 2 | N45: =IF(E45="-",0,LEN(E45)-LEN(SUBSTITUTE(E45,";",""))+1) -> 2 | O45: =SUM(M45:N45) -> 4 | P45: Impact | Q45: Product Excellence | R45: Easy | S45: -
A46: 64 | B46: Linting Duration | C46: - | D46: 201 | E46: - | F46: The duration needed to lint apps and packages locally or in a pipeline. | G46: quantitative | H46: System | I46: =VLOOKUP(H46,cardsort_group_IDs!A:B,2,0) -> 202 | J46: Build Time | K46: =VLOOKUP(J46,cardsort_subgroup_IDs!A:B,2,0) -> 303 | L46: =IF(E46="-",0,1)+IF(D46="-",0,2) -> 2 | M46: =IF(D46="-",0,LEN(D46)-LEN(SUBSTITUTE(D46,";",""))+1) -> 1 | N46: =IF(E46="-",0,LEN(E46)-LEN(SUBSTITUTE(E46,";",""))+1) -> 0 | O46: =SUM(M46:N46) -> 1 | P46: None | Q46: Developer Experience | R46: Easy | S46: -
A47: 65 | B47: Mean Time to Recover | C47: MTTR; Mean Time to Resolution; Time to Restore Services | D47: 501o; 131a; 131d; 131m; 202a; 511i; 511l | E47: 508; 506; 9; 50; 160; 131; 202; 182; 146 | F47: Mean Time to Recover (MTTR) is a key DevOps and IT reliability metric that measures the average time it takes to restore a system after a failure. It reflects how quickly teams can diagnose, fix, and recover from incidents. Time from bug report to fix deployment. Shows quality response capability. | G47: quantitative | H47: System | I47: =VLOOKUP(H47,cardsort_group_IDs!A:B,2,0) -> 202 | J47: Failure Recovery | K47: =VLOOKUP(J47,cardsort_subgroup_IDs!A:B,2,0) -> 325 | L47: =IF(E47="-",0,1)+IF(D47="-",0,2) -> 3 | M47: =IF(D47="-",0,LEN(D47)-LEN(SUBSTITUTE(D47,";",""))+1) -> 7 | N47: =IF(E47="-",0,LEN(E47)-LEN(SUBSTITUTE(E47,";",""))+1) -> 9 | O47: =SUM(M47:N47) -> 16 | P47: None | Q47: Organizational Effectiveness | R47: Easy | S47: -
A48: 67 | B48: Communication Network Density | C48: - | D48: 501m | E48: 503; 501 | F48: Network metrics that show who is connected to whom and how. | G48: quantitative | H48: Team | I48: =VLOOKUP(H48,cardsort_group_IDs!A:B,2,0) -> 206 | J48: Collaboration | K48: =VLOOKUP(J48,cardsort_subgroup_IDs!A:B,2,0) -> 326 | L48: =IF(E48="-",0,1)+IF(D48="-",0,2) -> 3 | M48: =IF(D48="-",0,LEN(D48)-LEN(SUBSTITUTE(D48,";",""))+1) -> 1 | N48: =IF(E48="-",0,LEN(E48)-LEN(SUBSTITUTE(E48,";",""))+1) -> 2 | O48: =SUM(M48:N48) -> 3 | P48: None | Q48: Organizational Effectiveness | R48: Moderate | S48: -
A49: 69 | B49: Number of Deployments | C49: Deployment Count; Deploy Count; Total Deployments | D49: 501g | E49: 31; 501 | F49: Measures the number of deployments. | G49: quantitative | H49: Customer | I49: =VLOOKUP(H49,cardsort_group_IDs!A:B,2,0) -> 208 | J49: Deployment Frequency | K49: =VLOOKUP(J49,cardsort_subgroup_IDs!A:B,2,0) -> 318 | L49: =IF(E49="-",0,1)+IF(D49="-",0,2) -> 3 | M49: =IF(D49="-",0,LEN(D49)-LEN(SUBSTITUTE(D49,";",""))+1) -> 1 | N49: =IF(E49="-",0,LEN(E49)-LEN(SUBSTITUTE(E49,";",""))+1) -> 2 | O49: =SUM(M49:N49) -> 3 | P49: None | Q49: Organizational Effectiveness | R49: Easy | S49: -
A50: 70 | B50: Number of Escaped Bugs | C50: Number of Issues Logged; Number of Bugs Post Release; Bugs Fixed; Introduced Bugs; Priority Tickets/Bugs Undertaken Mid-Sprint | D50: 232; 232a | E50: 9; 235; 21 | F50: Measures the number of defects or issues that escape testing and reach production. It measures the effectiveness of testing processes and helps identify weaknesses in quality assurance. | G50: quantitative | H50: Quality | I50: =VLOOKUP(H50,cardsort_group_IDs!A:B,2,0) -> 205 | J50: Test Coverage | K50: =VLOOKUP(J50,cardsort_subgroup_IDs!A:B,2,0) -> 309 | L50: =IF(E50="-",0,1)+IF(D50="-",0,2) -> 3 | M50: =IF(D50="-",0,LEN(D50)-LEN(SUBSTITUTE(D50,";",""))+1) -> 2 | N50: =IF(E50="-",0,LEN(E50)-LEN(SUBSTITUTE(E50,";",""))+1) -> 3 | O50: =SUM(M50:N50) -> 5 | P50: None | Q50: Product Excellence | R50: Easy | S50: 26; 29; 42; 133
A51: 71 | B51: Number of Handoffs | C51: Handoffs | D51: 501m | E51: 503; 501; 506 | F51: Measures how many times work is transferred between individuals, teams, or systems during a workflow. | G51: quantitative | H51: Process | I51: =VLOOKUP(H51,cardsort_group_IDs!A:B,2,0) -> 204 | J51: Efficiency | K51: =VLOOKUP(J51,cardsort_subgroup_IDs!A:B,2,0) -> 327 | L51: =IF(E51="-",0,1)+IF(D51="-",0,2) -> 3 | M51: =IF(D51="-",0,LEN(D51)-LEN(SUBSTITUTE(D51,";",""))+1) -> 1 | N51: =IF(E51="-",0,LEN(E51)-LEN(SUBSTITUTE(E51,";",""))+1) -> 3 | O51: =SUM(M51:N51) -> 4 | P51: None | Q51: Organizational Effectiveness | R51: Moderate | S51: -
A52: 72 | B52: Time for Onboarding New Hires | C52: - | D52: 501m | E52: 503; 501 | F52: Measures the onboarding time for new members, also including HR-related onboarding. | G52: quantitative | H52: Business | I52: =VLOOKUP(H52,cardsort_group_IDs!A:B,2,0) -> 201 | J52: HR | K52: =VLOOKUP(J52,cardsort_subgroup_IDs!A:B,2,0) -> 329 | L52: =IF(E52="-",0,1)+IF(D52="-",0,2) -> 3 | M52: =IF(D52="-",0,LEN(D52)-LEN(SUBSTITUTE(D52,";",""))+1) -> 1 | N52: =IF(E52="-",0,LEN(E52)-LEN(SUBSTITUTE(E52,";",""))+1) -> 2 | O52: =SUM(M52:N52) -> 3 | P52: None | Q52: Developer Experience | R52: Moderate | S52: 124
A53: 73 | B53: Operational Activity | C53: - | D53: 501m | E53: 503; 501 | F53: Refers to the routine tasks and processes required to maintain, monitor, and support software systems in production. These activities ensure the system remains stable, secure, and performant while minimizing downtime. | G53: quantitative | H53: System | I53: =VLOOKUP(H53,cardsort_group_IDs!A:B,2,0) -> 202 | J53: Reliability and Stability | K53: =VLOOKUP(J53,cardsort_subgroup_IDs!A:B,2,0) -> 304 | L53: =IF(E53="-",0,1)+IF(D53="-",0,2) -> 3 | M53: =IF(D53="-",0,LEN(D53)-LEN(SUBSTITUTE(D53,";",""))+1) -> 1 | N53: =IF(E53="-",0,LEN(E53)-LEN(SUBSTITUTE(E53,";",""))+1) -> 2 | O53: =SUM(M53:N53) -> 3 | P53: None | Q53: Organizational Effectiveness | R53: Moderate | S53: -
A54: 75 | B54: Service Readiness Score | C54: Service Operational Readiness Score | D54: 183a | E54: 183 | F54: A composite score assessing how well individual services meet operational standards (e.g., monitoring/alarm coverage, runbook completeness, on-call readiness, error-budget adherence) used to track production maturity across a microservices portfolio. | G54: quantitative | H54: Quality | I54: =VLOOKUP(H54,cardsort_group_IDs!A:B,2,0) -> 205 | J54: Code Quality | K54: =VLOOKUP(J54,cardsort_subgroup_IDs!A:B,2,0) -> 319 | L54: =IF(E54="-",0,1)+IF(D54="-",0,2) -> 3 | M54: =IF(D54="-",0,LEN(D54)-LEN(SUBSTITUTE(D54,";",""))+1) -> 1 | N54: =IF(E54="-",0,LEN(E54)-LEN(SUBSTITUTE(E54,";",""))+1) -> 1 | O54: =SUM(M54:N54) -> 2 | P54: None | Q54: Organizational Effectiveness | R54: Complex | S54: 95
A55: 76 | B55: Operational Health and Security Score | D55: - | E55: 514; 9 | F55: Tracks the operational health and security posture of production systems. As currently defined, this metric is vague and underspecified as it doesn't specify which signals are tracked or how they're aggregated. | G55: quantitative | H55: Business | I55: =VLOOKUP(H55,cardsort_group_IDs!A:B,2,0) -> 201 | J55: Performance | K55: =VLOOKUP(J55,cardsort_subgroup_IDs!A:B,2,0) -> 324 | L55: =IF(E55="-",0,1)+IF(D55="-",0,2) -> 1 | M55: =IF(D55="-",0,LEN(D55)-LEN(SUBSTITUTE(D55,";",""))+1) -> 0 | N55: =IF(E55="-",0,LEN(E55)-LEN(SUBSTITUTE(E55,";",""))+1) -> 2 | O55: =SUM(M55:N55) -> 2 | P55: None | Q55: Organizational Effectiveness | R55: Moderate | S55: -
A56: 78 | B56: Perceived Productivity | C56: Self-reported Productivity | D56: 501e; 501d; 501k; 5a; 203; 511b | E56: 5; 160; 501; 19; 39; 523 | F56: The self-reported productivity by an individual (might be aggregated on team level). | G56: qualitative | H56: Developer Enablement | I56: =VLOOKUP(H56,cardsort_group_IDs!A:B,2,0) -> 203 | J56: Ease of Delivery | K56: =VLOOKUP(J56,cardsort_subgroup_IDs!A:B,2,0) -> 313 | L56: =IF(E56="-",0,1)+IF(D56="-",0,2) -> 3 | M56: =IF(D56="-",0,LEN(D56)-LEN(SUBSTITUTE(D56,";",""))+1) -> 6 | N56: =IF(E56="-",0,LEN(E56)-LEN(SUBSTITUTE(E56,";",""))+1) -> 6 | O56: =SUM(M56:N56) -> 12 | P56: Impact | Q56: Developer Experience | R56: Easy | S56: -
A57: 79 | B57: Perceived Rate of Delivery | C57: - | D57: 501l | E57: 514; 501; 512 | F57: A subjective metric that reflects how fast stakeholders (e.g., customers, executives, or internal teams) believe software is being delivered, regardless of the actual speed. It’s influenced by communication, transparency, and user experience rather than just raw deployment frequency. | G57: qualitative | H57: Customer | I57: =VLOOKUP(H57,cardsort_group_IDs!A:B,2,0) -> 208 | J57: Deployment Frequency | K57: =VLOOKUP(J57,cardsort_subgroup_IDs!A:B,2,0) -> 318 | L57: =IF(E57="-",0,1)+IF(D57="-",0,2) -> 3 | M57: =IF(D57="-",0,LEN(D57)-LEN(SUBSTITUTE(D57,";",""))+1) -> 1 | N57: =IF(E57="-",0,LEN(E57)-LEN(SUBSTITUTE(E57,";",""))+1) -> 3 | O57: =SUM(M57:N57) -> 4 | P57: Impact | Q57: Organizational Effectiveness | R57: Easy | S57: -
A58: 80 | B58: Perceived Software Quality | C58: - | D58: - | E58: 514 | F58: Evaluates how users perceive the overall quality of a software product. This metric is subjective and focuses on user satisfaction, usability, and the software’s ability to meet user expectations. It often involves collecting feedback through surveys, such as Customer Satisfaction (CSAT) scores, which measure user perceptions of quality based on their experience with the product. | G58: qualitative | H58: Customer | I58: =VLOOKUP(H58,cardsort_group_IDs!A:B,2,0) -> 208 | J58: Product Quality | K58: =VLOOKUP(J58,cardsort_subgroup_IDs!A:B,2,0) -> 317 | L58: =IF(E58="-",0,1)+IF(D58="-",0,2) -> 1 | M58: =IF(D58="-",0,LEN(D58)-LEN(SUBSTITUTE(D58,";",""))+1) -> 0 | N58: =IF(E58="-",0,LEN(E58)-LEN(SUBSTITUTE(E58,";",""))+1) -> 1 | O58: =SUM(M58:N58) -> 1 | P58: None | Q58: Product Excellence | R58: Easy | S58: -
A59: 82 | B59: Regrettable Attrition Rate | C59: Percentage of Regrettable Attrition | D59: - | E59: 514 | F59: Refers to the voluntary departure of highly valued employees whose loss significantly impacts the organization. | G59: quantitative | H59: Business | I59: =VLOOKUP(H59,cardsort_group_IDs!A:B,2,0) -> 201 | J59: HR | K59: =VLOOKUP(J59,cardsort_subgroup_IDs!A:B,2,0) -> 329 | L59: =IF(E59="-",0,1)+IF(D59="-",0,2) -> 1 | M59: =IF(D59="-",0,LEN(D59)-LEN(SUBSTITUTE(D59,";",""))+1) -> 0 | N59: =IF(E59="-",0,LEN(E59)-LEN(SUBSTITUTE(E59,";",""))+1) -> 1 | O59: =SUM(M59:N59) -> 1 | P59: None | Q59: Organizational Effectiveness | R59: Moderate | S59: -
A60: 83 | B60: Percentage of Time Spent on New Capabilities | C60: Innovation rate | D60: 511a; 511j; 511h | E60: 514; 9 | F60: Measures the proportion of a team's time dedicated to building new features or capabilities, as opposed to activities like maintenance, bug fixes, or refactoring. | G60: quantitative | H60: Developer Enablement | I60: =VLOOKUP(H60,cardsort_group_IDs!A:B,2,0) -> 203 | J60: Upskilling | K60: =VLOOKUP(J60,cardsort_subgroup_IDs!A:B,2,0) -> 328 | L60: =IF(E60="-",0,1)+IF(D60="-",0,2) -> 3 | M60: =IF(D60="-",0,LEN(D60)-LEN(SUBSTITUTE(D60,";",""))+1) -> 3 | N60: =IF(E60="-",0,LEN(E60)-LEN(SUBSTITUTE(E60,";",""))+1) -> 2 | O60: =SUM(M60:N60) -> 5 | P60: Impact | Q60: Organizational Effectiveness | R60: Moderate | S60: 124
A61: 87 | B61: Pull Request Cycle Time | C61: - | D61: 501h; 516c | E61: 501; 183; 522 | F61: Measures the total time a pull request spends in all stages of the development pipeline, from the first commit to when the pull request is merged into the codebase (e.g. to the main/production branch). It provides insights into the efficiency of the code review and merging process, helping teams identify bottlenecks and improve workflows. | G61: quantitative | H61: Process | I61: =VLOOKUP(H61,cardsort_group_IDs!A:B,2,0) -> 204 | J61: Cycle Time | K61: =VLOOKUP(J61,cardsort_subgroup_IDs!A:B,2,0) -> 306 | L61: =IF(E61="-",0,1)+IF(D61="-",0,2) -> 3 | M61: =IF(D61="-",0,LEN(D61)-LEN(SUBSTITUTE(D61,";",""))+1) -> 2 | N61: =IF(E61="-",0,LEN(E61)-LEN(SUBSTITUTE(E61,";",""))+1) -> 3 | O61: =SUM(M61:N61) -> 5 | P61: None | Q61: Organizational Effectiveness | R61: Easy | S61: 9
A62: 88 | B62: Post-Submission Edit Ratio | C62: Edit Ratio; Pull Request Maturity; Total Number of Changelists | D62: 32a; 516c | E62: 241; 32 | F62: The percentage of code changes within a pull request that occur after it has been submitted for review. Aims to minimize back-and-forth during review, enabling quicker, more decisive reviews and faster integration. | G62: quantitative | H62: Quality | I62: =VLOOKUP(H62,cardsort_group_IDs!A:B,2,0) -> 205 | J62: Code Quality | K62: =VLOOKUP(J62,cardsort_subgroup_IDs!A:B,2,0) -> 319 | L62: =IF(E62="-",0,1)+IF(D62="-",0,2) -> 3 | M62: =IF(D62="-",0,LEN(D62)-LEN(SUBSTITUTE(D62,";",""))+1) -> 2 | N62: =IF(E62="-",0,LEN(E62)-LEN(SUBSTITUTE(E62,";",""))+1) -> 2 | O62: =SUM(M62:N62) -> 4 | P62: None | Q62: Product Excellence | R62: Easy | S62: -
A63: 89 | B63: Pull Request Size | C63: PR Size | D63: 501m; 131l; 516c; 202a | E63: 501; 131; 202; 520 | F63: An indicator of overall code review efficiency. Small PRs mean faster pickup time, reviews, and cycles–translating to faster time to value. Larger PRs often result in fewer meaningful comments. For example, PRs with more than 250 lines of code could be tagged. | G63: quantitative | H63: Quality | I63: =VLOOKUP(H63,cardsort_group_IDs!A:B,2,0) -> 205 | J63: Code Quality | K63: =VLOOKUP(J63,cardsort_subgroup_IDs!A:B,2,0) -> 319 | L63: =IF(E63="-",0,1)+IF(D63="-",0,2) -> 3 | M63: =IF(D63="-",0,LEN(D63)-LEN(SUBSTITUTE(D63,";",""))+1) -> 4 | N63: =IF(E63="-",0,LEN(E63)-LEN(SUBSTITUTE(E63,";",""))+1) -> 4 | O63: =SUM(M63:N63) -> 8 | P63: AI Impact | Q63: Organizational Effectiveness | R63: Easy | S63: -
A64: 90 | B64: Custom Quality Metric | C64: Unit Test Quality; Code Quality; Process Quality; System Quality; Code Maintainability | D64: 501m; 5a; 511a; 511f | E64: 503; 9; 17; 5; 115; 501; 115; 183; 182; 512; 522 | F64: Relates to code reliability, maintainability, and alignment with user/business outcomes. It may be measured through metrics that assess both technical rigor and real-world impact, emphasizing sustainable practices over superficial outputs. Usually highly company-specific implementation. | G64: qualitative | H64: Quality | I64: =VLOOKUP(H64,cardsort_group_IDs!A:B,2,0) -> 205 | J64: Code Quality | K64: =VLOOKUP(J64,cardsort_subgroup_IDs!A:B,2,0) -> 319 | L64: =IF(E64="-",0,1)+IF(D64="-",0,2) -> 3 | M64: =IF(D64="-",0,LEN(D64)-LEN(SUBSTITUTE(D64,";",""))+1) -> 4 | N64: =IF(E64="-",0,LEN(E64)-LEN(SUBSTITUTE(E64,";",""))+1) -> 11 | O64: =SUM(M64:N64) -> 15 | P64: Impact | Q64: Product Excellence | R64: Complex | S64: -
A65: 91 | B65: Quality of Documentation | C65: Self-Service Documentation; Written Communication Effectiveness Through Design Documents | D65: 501h | E65: 506; 501; 183 | F65: Measures how well documentation supports the software development process, particularly in enabling developers to work efficiently and effectively. | G65: qualitative | H65: Process | I65: =VLOOKUP(H65,cardsort_group_IDs!A:B,2,0) -> 204 | J65: Self-Service and Documentation | K65: =VLOOKUP(J65,cardsort_subgroup_IDs!A:B,2,0) -> 320 | L65: =IF(E65="-",0,1)+IF(D65="-",0,2) -> 3 | M65: =IF(D65="-",0,LEN(D65)-LEN(SUBSTITUTE(D65,";",""))+1) -> 1 | N65: =IF(E65="-",0,LEN(E65)-LEN(SUBSTITUTE(E65,";",""))+1) -> 3 | O65: =SUM(M65:N65) -> 4 | P65: None | Q65: Product Excellence | R65: Moderate | S65: -
A66: 92 | B66: Quality of Code Reviews | C66: - | D66: 501m | E66: 503; 501 | F66: Measures quality of code reviews contributed by team members. | G66: qualitative | H66: Team | I66: =VLOOKUP(H66,cardsort_group_IDs!A:B,2,0) -> 206 | J66: Collaboration | K66: =VLOOKUP(J66,cardsort_subgroup_IDs!A:B,2,0) -> 326 | L66: =IF(E66="-",0,1)+IF(D66="-",0,2) -> 3 | M66: =IF(D66="-",0,LEN(D66)-LEN(SUBSTITUTE(D66,";",""))+1) -> 1 | N66: =IF(E66="-",0,LEN(E66)-LEN(SUBSTITUTE(E66,";",""))+1) -> 2 | O66: =SUM(M66:N66) -> 3 | P66: None | Q66: Product Excellence | R66: Moderate | S66: -
A67: 93 | B67: R&D as Percentage of Revenue | C67: - | D67: - | E67: 514 | F67: Measures how much of a company’s total revenue is invested in research and development (R&D). | G67: quantitative | H67: Business | I67: =VLOOKUP(H67,cardsort_group_IDs!A:B,2,0) -> 201 | J67: Optimal Resource Allocation | K67: =VLOOKUP(J67,cardsort_subgroup_IDs!A:B,2,0) -> 302 | L67: =IF(E67="-",0,1)+IF(D67="-",0,2) -> 1 | M67: =IF(D67="-",0,LEN(D67)-LEN(SUBSTITUTE(D67,";",""))+1) -> 0 | N67: =IF(E67="-",0,LEN(E67)-LEN(SUBSTITUTE(E67,";",""))+1) -> 1 | O67: =SUM(M67:N67) -> 1 | P67: None | Q67: Organizational Effectiveness | R67: Easy | S67: -
A68: 94 | B68: Release Frequency | C68: Release Count | D68: 131b; 131l | E68: 31; 131 | F68: How often features reach users (independent of deployment frequency, such as when feature flags or staged rollouts are used). | G68: quantitative | H68: Customer | I68: =VLOOKUP(H68,cardsort_group_IDs!A:B,2,0) -> 208 | J68: Deployment Frequency | K68: =VLOOKUP(J68,cardsort_subgroup_IDs!A:B,2,0) -> 318 | L68: =IF(E68="-",0,1)+IF(D68="-",0,2) -> 3 | M68: =IF(D68="-",0,LEN(D68)-LEN(SUBSTITUTE(D68,";",""))+1) -> 2 | N68: =IF(E68="-",0,LEN(E68)-LEN(SUBSTITUTE(E68,";",""))+1) -> 2 | O68: =SUM(M68:N68) -> 4 | P68: None | Q68: Organizational Effectiveness | R68: Easy | S68: 30; 79
A69: 95 | B69: Reliability Score | C69: Availability; Latency; Performance; Scalability | D69: 183a | E69: - | F69: A composite reliability measure covering availability (uptime %), latency (response time percentiles), performance, and scalability (behavior under load). DORA's original 2021 methodology measured this via self-rated survey ('are you meeting your reliability targets?'), but the underlying components can also be tracked quantitatively via system telemetry. | G69: both | H69: System | I69: =VLOOKUP(H69,cardsort_group_IDs!A:B,2,0) -> 202 | J69: Reliability and Stability | K69: =VLOOKUP(J69,cardsort_subgroup_IDs!A:B,2,0) -> 304 | L69: =IF(E69="-",0,1)+IF(D69="-",0,2) -> 2 | M69: =IF(D69="-",0,LEN(D69)-LEN(SUBSTITUTE(D69,";",""))+1) -> 1 | N69: =IF(E69="-",0,LEN(E69)-LEN(SUBSTITUTE(E69,";",""))+1) -> 0 | O69: =SUM(M69:N69) -> 1 | P69: None | Q69: Product Excellence | R69: Moderate | S69: 75; 109
A70: 97 | B70: Response Time | C70: - | D70: - | E70: 508 | F70: Measures the server’s speed in fulfilling user requests. | G70: quantitative | H70: System | I70: =VLOOKUP(H70,cardsort_group_IDs!A:B,2,0) -> 202 | J70: Performance | K70: =VLOOKUP(J70,cardsort_subgroup_IDs!A:B,2,0) -> 324 | L70: =IF(E70="-",0,1)+IF(D70="-",0,2) -> 1 | M70: =IF(D70="-",0,LEN(D70)-LEN(SUBSTITUTE(D70,";",""))+1) -> 0 | N70: =IF(E70="-",0,LEN(E70)-LEN(SUBSTITUTE(E70,";",""))+1) -> 1 | O70: =SUM(M70:N70) -> 1 | P70: None | Q70: Product Excellence | R70: Easy | S70: -
A71: 98 | B71: Employee Retention Rate | C71: Employment Retention | D71: 209 | E71: 506 | F71: How well an organization retains its employees over a given period. | G71: quantitative | H71: Business | I71: =VLOOKUP(H71,cardsort_group_IDs!A:B,2,0) -> 201 | J71: HR | K71: =VLOOKUP(J71,cardsort_subgroup_IDs!A:B,2,0) -> 329 | L71: =IF(E71="-",0,1)+IF(D71="-",0,2) -> 3 | M71: =IF(D71="-",0,LEN(D71)-LEN(SUBSTITUTE(D71,";",""))+1) -> 1 | N71: =IF(E71="-",0,LEN(E71)-LEN(SUBSTITUTE(E71,";",""))+1) -> 1 | O71: =SUM(M71:N71) -> 2 | P71: None | Q71: Organizational Effectiveness | R71: Easy | S71: -
A72: 99 | B72: Revenue Growth Rate | C72: - | D72: - | E72: 508 | F72: Measures the growth of revenue, such as year over year. | G72: quantitative | H72: Business | I72: =VLOOKUP(H72,cardsort_group_IDs!A:B,2,0) -> 201 | J72: Performance | K72: =VLOOKUP(J72,cardsort_subgroup_IDs!A:B,2,0) -> 324 | L72: =IF(E72="-",0,1)+IF(D72="-",0,2) -> 1 | M72: =IF(D72="-",0,LEN(D72)-LEN(SUBSTITUTE(D72,";",""))+1) -> 0 | N72: =IF(E72="-",0,LEN(E72)-LEN(SUBSTITUTE(E72,";",""))+1) -> 1 | O72: =SUM(M72:N72) -> 1 | P72: None | Q72: Organizational Effectiveness | R72: Easy | S72: -
A73: 100 | B73: Revenue per Engineer | C73: - | D73: - | E73: 514 | F73: Measures the average revenue per engineer. | G73: quantitative | H73: Business | I73: =VLOOKUP(H73,cardsort_group_IDs!A:B,2,0) -> 201 | J73: Performance | K73: =VLOOKUP(J73,cardsort_subgroup_IDs!A:B,2,0) -> 324 | L73: =IF(E73="-",0,1)+IF(D73="-",0,2) -> 1 | M73: =IF(D73="-",0,LEN(D73)-LEN(SUBSTITUTE(D73,";",""))+1) -> 0 | N73: =IF(E73="-",0,LEN(E73)-LEN(SUBSTITUTE(E73,";",""))+1) -> 1 | O73: =SUM(M73:N73) -> 1 | P73: None | Q73: Organizational Effectiveness | R73: Easy | S73: -
A74: 102 | B74: Dependency Update Automation Rate | C74: Self-Serve Dependency Maintenance | D74: 501h; 519 | E74: 501 | F74: The share of dependency updates (internal services and third-party/open-source libraries) that are applied automatically without requiring manual developer intervention. Used as a proxy for how much interrupt-driven toil developers face for keeping their stack current. Measured via developer survey. | G74: both | H74: Process | I74: =VLOOKUP(H74,cardsort_group_IDs!A:B,2,0) -> 204 | J74: Self-Service and Documentation | K74: =VLOOKUP(J74,cardsort_subgroup_IDs!A:B,2,0) -> 320 | L74: =IF(E74="-",0,1)+IF(D74="-",0,2) -> 3 | M74: =IF(D74="-",0,LEN(D74)-LEN(SUBSTITUTE(D74,";",""))+1) -> 2 | N74: =IF(E74="-",0,LEN(E74)-LEN(SUBSTITUTE(E74,";",""))+1) -> 1 | O74: =SUM(M74:N74) -> 3 | P74: None | Q74: Developer Experience | R74: Moderate | S74: -
A75: 104 | B75: Tool Sentiment Score | C75: - | D75: 501j; 501l | E75: - | F75: Developers' emotional responses and perceptions of their interactions with tools, documentation, and workflows. It focuses on how developers feel about using the platform and whether they find it empowering, frustrating, or aligned with their goals. | G75: qualitative | H75: Developer Enablement | I75: =VLOOKUP(H75,cardsort_group_IDs!A:B,2,0) -> 203 | J75: Satisfaction | K75: =VLOOKUP(J75,cardsort_subgroup_IDs!A:B,2,0) -> 322 | L75: =IF(E75="-",0,1)+IF(D75="-",0,2) -> 2 | M75: =IF(D75="-",0,LEN(D75)-LEN(SUBSTITUTE(D75,";",""))+1) -> 2 | N75: =IF(E75="-",0,LEN(E75)-LEN(SUBSTITUTE(E75,";",""))+1) -> 0 | O75: =SUM(M75:N75) -> 2 | P75: None | Q75: Developer Experience | R75: Moderate | S75: -
A76: 107 | B76: Speed | C76: - | D76: 501b; 5a | E76: 5; 501; 115; 183; 522 | F76: Relates to how quickly software engineers can accomplish their tasks, focusing on the efficiency of workflows and processes that enable rapid delivery without compromising quality. This includes quantiative metrics (logs for task durations, deployment statistics, and CI/CD pipeline metrics) and qualitative metrics (developer surveys, diary studies, and interviews to understand perceptions and identify pain points). | G76: both | H76: Process | I76: =VLOOKUP(H76,cardsort_group_IDs!A:B,2,0) -> 204 | J76: Cycle Time | K76: =VLOOKUP(J76,cardsort_subgroup_IDs!A:B,2,0) -> 306 | L76: =IF(E76="-",0,1)+IF(D76="-",0,2) -> 3 | M76: =IF(D76="-",0,LEN(D76)-LEN(SUBSTITUTE(D76,";",""))+1) -> 2 | N76: =IF(E76="-",0,LEN(E76)-LEN(SUBSTITUTE(E76,";",""))+1) -> 5 | O76: =SUM(M76:N76) -> 7 | P76: None | Q76: Organizational Effectiveness | R76: Moderate | S76: -
A77: 108 | B77: Velocity | C77: Sprint Velocity; Developer Velocity | D77: 501k; 131e; 199; 232a; 232 | E77: 105; 501; 131 | F77: The amount of work completed per sprint/time period. Helps with planning and tracking. | G77: quantitative | H77: Process | I77: =VLOOKUP(H77,cardsort_group_IDs!A:B,2,0) -> 204 | J77: Efficiency | K77: =VLOOKUP(J77,cardsort_subgroup_IDs!A:B,2,0) -> 327 | L77: =IF(E77="-",0,1)+IF(D77="-",0,2) -> 3 | M77: =IF(D77="-",0,LEN(D77)-LEN(SUBSTITUTE(D77,";",""))+1) -> 5 | N77: =IF(E77="-",0,LEN(E77)-LEN(SUBSTITUTE(E77,";",""))+1) -> 3 | O77: =SUM(M77:N77) -> 8 | P77: None | Q77: Organizational Effectiveness | R77: Easy | S77: -
A78: 109 | B78: Service Uptime Percentage | C78: Stability; Stability of Services; Stability of Apps; Production Incidents; Production Downtime; System Uptime; Availability | D78: 501b; 501a; 131k; 131j | E78: 508; 501; 131 | F78: Measures the percentage of time services and apps are available/operational, and the rate of production incidents (outages, change failures, time-to-recovery): the system's track record of staying up and recovering quickly. An improved rate reduces time teams spend addressing bugs and outages, increasing operational efficiency. | G78: quantitative | H78: System | I78: =VLOOKUP(H78,cardsort_group_IDs!A:B,2,0) -> 202 | J78: Reliability and Stability | K78: =VLOOKUP(J78,cardsort_subgroup_IDs!A:B,2,0) -> 304 | L78: =IF(E78="-",0,1)+IF(D78="-",0,2) -> 3 | M78: =IF(D78="-",0,LEN(D78)-LEN(SUBSTITUTE(D78,";",""))+1) -> 4 | N78: =IF(E78="-",0,LEN(E78)-LEN(SUBSTITUTE(E78,";",""))+1) -> 3 | O78: =SUM(M78:N78) -> 7 | P78: None | Q78: Product Excellence | R78: Easy | S78: 95; 65
A79: 112 | B79: Talent Capability Score | C79: - | D79: - | E79: 506 | F79: Evaluates the alignment of workforce skills with technical/domain/operational needs; identifies gaps constraining delivery or innovation. | G79: qualitative | H79: Developer Enablement | I79: =VLOOKUP(H79,cardsort_group_IDs!A:B,2,0) -> 203 | J79: Upskilling | K79: =VLOOKUP(J79,cardsort_subgroup_IDs!A:B,2,0) -> 328 | L79: =IF(E79="-",0,1)+IF(D79="-",0,2) -> 1 | M79: =IF(D79="-",0,LEN(D79)-LEN(SUBSTITUTE(D79,";",""))+1) -> 0 | N79: =IF(E79="-",0,LEN(E79)-LEN(SUBSTITUTE(E79,";",""))+1) -> 1 | O79: =SUM(M79:N79) -> 1 | P79: Impact | Q79: Organizational Effectiveness | R79: Complex | S79: 113
A80: 113 | B80: Upskilling Rate | C80: Technical expertise development; Skill development | D80: - | E80: 512 | F80: Measures the rate/volume of upskilling and cross-training activity (e.g., courses completed, certifications, AI-accelerated learning) within the organization. | G80: quantitative | H80: Developer Enablement | I80: =VLOOKUP(H80,cardsort_group_IDs!A:B,2,0) -> 203 | J80: Upskilling | K80: =VLOOKUP(J80,cardsort_subgroup_IDs!A:B,2,0) -> 328 | L80: =IF(E80="-",0,1)+IF(D80="-",0,2) -> 1 | M80: =IF(D80="-",0,LEN(D80)-LEN(SUBSTITUTE(D80,";",""))+1) -> 0 | N80: =IF(E80="-",0,LEN(E80)-LEN(SUBSTITUTE(E80,";",""))+1) -> 1 | O80: =SUM(M80:N80) -> 1 | P80: Impact | Q80: Organizational Effectiveness | R80: Moderate | S80: 112
A81: 114 | B81: Task Completion Rate | C81: Task Completion Rate; Story Points Completed; Function Points; Completion Percentage / Completion Time; Average Number of UFPs Completed; Story Points per Sprnt; Function Points per Month; Product Delivery Rate; Number of Requirements Met; Completed Goals to Planned Goals Ratio; Sprint Burndown Rates | D81: 232a; 232 | E81: 506; 9; 13; 15; 45; 87; 233; 235; 236; 237; 238; 513; 523 | F81: Measures the rate of work completion — the volume of task units (e.g., story points, function points, requirements) completed per individual or team, typically tracked per sprint or time period, and optionally expressed as a percentage of planned work completed. | G81: quantitative | H81: Output | I81: =VLOOKUP(H81,cardsort_group_IDs!A:B,2,0) -> 207 | J81: Produced Output | K81: =VLOOKUP(J81,cardsort_subgroup_IDs!A:B,2,0) -> 312 | L81: =IF(E81="-",0,1)+IF(D81="-",0,2) -> 3 | M81: =IF(D81="-",0,LEN(D81)-LEN(SUBSTITUTE(D81,";",""))+1) -> 2 | N81: =IF(E81="-",0,LEN(E81)-LEN(SUBSTITUTE(E81,";",""))+1) -> 13 | O81: =SUM(M81:N81) -> 15 | P81: Impact | Q81: Organizational Effectiveness | R81: Easy | S81: -
A82: 115 | B82: Team Collaboration Effectiveness | C82: Cross-team Contribution Rate; Communication Responsiveness | D82: - | E82: 183 | F82: Assesses how well a team communicates and coordinates, typically via signals such as code review turnaround, cross-team contribution patterns, response/communication latency, or async documentation practices — often supplemented by self-reported survey scores rather than a single quantitative figure. | G82: both | H82: Team | I82: =VLOOKUP(H82,cardsort_group_IDs!A:B,2,0) -> 206 | J82: Collaboration | K82: =VLOOKUP(J82,cardsort_subgroup_IDs!A:B,2,0) -> 326 | L82: =IF(E82="-",0,1)+IF(D82="-",0,2) -> 1 | M82: =IF(D82="-",0,LEN(D82)-LEN(SUBSTITUTE(D82,";",""))+1) -> 0 | N82: =IF(E82="-",0,LEN(E82)-LEN(SUBSTITUTE(E82,";",""))+1) -> 1 | O82: =SUM(M82:N82) -> 1 | P82: None | Q82: Organizational Effectiveness | R82: Complex | S82: 17; 121
A83: 116 | B83: Technical Debt Ratio | C83: Technical Debt; Time Spent Remediating Techical Debt; Tech Debt | D83: 131f; 131g; 516c | E83: 70; 131; 524a; 524b | F83: Is an estimate of maintenance burden in codebase. It expresses the cost of fixing existing technical debt as a proportion of the total cost of developing the software (i.e. remediation cost ÷ development cost). | G83: quantitative | H83: Quality | I83: =VLOOKUP(H83,cardsort_group_IDs!A:B,2,0) -> 205 | J83: Maintenance Burden | K83: =VLOOKUP(J83,cardsort_subgroup_IDs!A:B,2,0) -> 331 | L83: =IF(E83="-",0,1)+IF(D83="-",0,2) -> 3 | M83: =IF(D83="-",0,LEN(D83)-LEN(SUBSTITUTE(D83,";",""))+1) -> 3 | N83: =IF(E83="-",0,LEN(E83)-LEN(SUBSTITUTE(E83,";",""))+1) -> 4 | O83: =SUM(M83:N83) -> 7 | P83: None | Q83: Product Excellence | R83: Moderate | S83: 163
A84: 117 | B84: Test Coverage | C84: Code Coverage Percent | D84: 131k; 511i | E84: 105; 234; 235; 131 | F84: The percentage of code covered by automated tests. Shows confidence in change safety. | G84: quantitative | H84: Quality | I84: =VLOOKUP(H84,cardsort_group_IDs!A:B,2,0) -> 205 | J84: Test Coverage | K84: =VLOOKUP(J84,cardsort_subgroup_IDs!A:B,2,0) -> 309 | L84: =IF(E84="-",0,1)+IF(D84="-",0,2) -> 3 | M84: =IF(D84="-",0,LEN(D84)-LEN(SUBSTITUTE(D84,";",""))+1) -> 2 | N84: =IF(E84="-",0,LEN(E84)-LEN(SUBSTITUTE(E84,";",""))+1) -> 4 | O84: =SUM(M84:N84) -> 6 | P84: Impact | Q84: Product Excellence | R84: Easy | S84: -
A85: 118 | B85: Test Runner Duration | C85: - | D85: 201 | E85: - | F85: Measures the duration to run tests for various apps and packages locally. | G85: quantitative | H85: System | I85: =VLOOKUP(H85,cardsort_group_IDs!A:B,2,0) -> 202 | J85: Test Time | K85: =VLOOKUP(J85,cardsort_subgroup_IDs!A:B,2,0) -> 332 | L85: =IF(E85="-",0,1)+IF(D85="-",0,2) -> 2 | M85: =IF(D85="-",0,LEN(D85)-LEN(SUBSTITUTE(D85,";",""))+1) -> 1 | N85: =IF(E85="-",0,LEN(E85)-LEN(SUBSTITUTE(E85,";",""))+1) -> 0 | O85: =SUM(M85:N85) -> 1 | P85: None | Q85: Developer Experience | R85: Easy | S85: -
A86: 120 | B86: Value-Added Time vs. Wait Time | C86: Value-Added Time; Wait Time | D86: 501m | E86: 503; 501 | F86: Per the SPACE framework, decomposes the time work spends in a system into value-added time (actively being worked on) and wait time (idle — in queues, blocked, or awaiting handoff), distinguishing productive flow from delay. | G86: quantitative | H86: Process | I86: =VLOOKUP(H86,cardsort_group_IDs!A:B,2,0) -> 204 | J86: Cycle Time | K86: =VLOOKUP(J86,cardsort_subgroup_IDs!A:B,2,0) -> 306 | L86: =IF(E86="-",0,1)+IF(D86="-",0,2) -> 3 | M86: =IF(D86="-",0,LEN(D86)-LEN(SUBSTITUTE(D86,";",""))+1) -> 1 | N86: =IF(E86="-",0,LEN(E86)-LEN(SUBSTITUTE(E86,";",""))+1) -> 2 | O86: =SUM(M86:N86) -> 3 | P86: None | Q86: Organizational Effectiveness | R86: Moderate | S86: 62
A87: 121 | B87: Time Spent in Code Review | C87: PR Time in Review; Code Review Time; Review Time; Median Wall-Clock Review Time; Median Wall-Clock Merge Time | D87: 131s; 131t; 32a; 511b | E87: 9; 192; 32; 131; 520 | F87: Measures the time developers spend reviewing others’ code. | G87: quantitative | H87: Process | I87: =VLOOKUP(H87,cardsort_group_IDs!A:B,2,0) -> 204 | J87: Cycle Time | K87: =VLOOKUP(J87,cardsort_subgroup_IDs!A:B,2,0) -> 306 | L87: =IF(E87="-",0,1)+IF(D87="-",0,2) -> 3 | M87: =IF(D87="-",0,LEN(D87)-LEN(SUBSTITUTE(D87,";",""))+1) -> 4 | N87: =IF(E87="-",0,LEN(E87)-LEN(SUBSTITUTE(E87,";",""))+1) -> 5 | O87: =SUM(M87:N87) -> 9 | P87: Impact | Q87: Organizational Effectiveness | R87: Easy | S87: -
A88: 122 | B88: Time to Market for New Features | C88: Time to Release; Feature Delivery Time | D88: 232a; 511r; 232 | E88: 508; 237 | F88: Measures the duration from the initial conception of a feature to its availability for end-users. | G88: quantitative | H88: Process | I88: =VLOOKUP(H88,cardsort_group_IDs!A:B,2,0) -> 204 | J88: Cycle Time | K88: =VLOOKUP(J88,cardsort_subgroup_IDs!A:B,2,0) -> 306 | L88: =IF(E88="-",0,1)+IF(D88="-",0,2) -> 3 | M88: =IF(D88="-",0,LEN(D88)-LEN(SUBSTITUTE(D88,";",""))+1) -> 3 | N88: =IF(E88="-",0,LEN(E88)-LEN(SUBSTITUTE(E88,";",""))+1) -> 2 | O88: =SUM(M88:N88) -> 5 | P88: Impact | Q88: Organizational Effectiveness | R88: Moderate | S88: 83
A89: 124 | B89: Time to Nth Pull Request | C89: Time to First Commit; Time to technical ability to commit; Time to Xth Pull Request; Time to Xth PR | D89: 202a; 131i; 131g; 516c; 518 | E89: 514; 131; 202; 146 | F89: Measures the time it takes for a new engineer to create their Nth pull request (PR) after joining a development team. For example, the time to 1st and 10th PR at Spotify. | G89: quantitative | H89: Developer Enablement | I89: =VLOOKUP(H89,cardsort_group_IDs!A:B,2,0) -> 203 | J89: Onboarding | K89: =VLOOKUP(J89,cardsort_subgroup_IDs!A:B,2,0) -> 323 | L89: =IF(E89="-",0,1)+IF(D89="-",0,2) -> 3 | M89: =IF(D89="-",0,LEN(D89)-LEN(SUBSTITUTE(D89,";",""))+1) -> 5 | N89: =IF(E89="-",0,LEN(E89)-LEN(SUBSTITUTE(E89,";",""))+1) -> 4 | O89: =SUM(M89:N89) -> 9 | P89: None | Q89: Developer Experience | R89: Moderate | S89: 72
A90: 126 | B90: Deployments per Developer | C90: Number of Deployments per Developer | D90: 501k | E90: 501 | F90: Quantifies the amount of weekly deployments per developer. | G90: quantitative | H90: Output | I90: =VLOOKUP(H90,cardsort_group_IDs!A:B,2,0) -> 207 | J90: Produced Output | K90: =VLOOKUP(J90,cardsort_subgroup_IDs!A:B,2,0) -> 312 | L90: =IF(E90="-",0,1)+IF(D90="-",0,2) -> 3 | M90: =IF(D90="-",0,LEN(D90)-LEN(SUBSTITUTE(D90,";",""))+1) -> 1 | N90: =IF(E90="-",0,LEN(E90)-LEN(SUBSTITUTE(E90,";",""))+1) -> 1 | O90: =SUM(M90:N90) -> 2 | P90: None | Q90: Organizational Effectiveness | R90: Easy | S90: -
A91: 127 | B91: Code Reviews per Developer | C91: Number of Comments; PR Review Comments and Requests for Changes | D91: 501n; 516c | E91: 9; 31 | F91: Quantifies the number of weekly code reviews per developer. | G91: quantitative | H91: Output | I91: =VLOOKUP(H91,cardsort_group_IDs!A:B,2,0) -> 207 | J91: Produced Output | K91: =VLOOKUP(J91,cardsort_subgroup_IDs!A:B,2,0) -> 312 | L91: =IF(E91="-",0,1)+IF(D91="-",0,2) -> 3 | M91: =IF(D91="-",0,LEN(D91)-LEN(SUBSTITUTE(D91,";",""))+1) -> 2 | N91: =IF(E91="-",0,LEN(E91)-LEN(SUBSTITUTE(E91,";",""))+1) -> 2 | O91: =SUM(M91:N91) -> 4 | P91: None | Q91: Organizational Effectiveness | R91: Easy | S91: 17; 121; 92; 129; 154
A92: 128 | B92: Design Docs per Developer | C92: Number of Design Docs Generated per Developer | D92: 501n | E92: 501 | F92: Quantifies the weekly number of design documents generated per engineer. | G92: quantitative | H92: Output | I92: =VLOOKUP(H92,cardsort_group_IDs!A:B,2,0) -> 207 | J92: Produced Output | K92: =VLOOKUP(J92,cardsort_subgroup_IDs!A:B,2,0) -> 312 | L92: =IF(E92="-",0,1)+IF(D92="-",0,2) -> 3 | M92: =IF(D92="-",0,LEN(D92)-LEN(SUBSTITUTE(D92,";",""))+1) -> 1 | N92: =IF(E92="-",0,LEN(E92)-LEN(SUBSTITUTE(E92,";",""))+1) -> 1 | O92: =SUM(M92:N92) -> 2 | P92: None | Q92: Organizational Effectiveness | R92: Easy | S92: -
A93: 129 | B93: Throughput | C93: Delivery Throughput; Weekly Number of Diffs; Weekly Number of PRs; Number of Changes | D93: 501n; 501j; 209; 511e; 511g; 511a; 511c; 511d; 511e; 511f; 511g; 511j; 511k; 511m; 511n; 511p | E93: 9; 36; 52; 62; 243; 244; 160; 501; 183; 512 | F93: Quantifies the number of features, stories, PRs / diffs, … completed per developer within a time interval (e.g. week). | G93: quantitative | H93: Output | I93: =VLOOKUP(H93,cardsort_group_IDs!A:B,2,0) -> 207 | J93: Produced Output | K93: =VLOOKUP(J93,cardsort_subgroup_IDs!A:B,2,0) -> 312 | L93: =IF(E93="-",0,1)+IF(D93="-",0,2) -> 3 | M93: =IF(D93="-",0,LEN(D93)-LEN(SUBSTITUTE(D93,";",""))+1) -> 16 | N93: =IF(E93="-",0,LEN(E93)-LEN(SUBSTITUTE(E93,";",""))+1) -> 10 | O93: =SUM(M93:N93) -> 26 | P93: Impact | Q93: Organizational Effectiveness | R93: Easy | S93: -
A94: 130 | B94: Time Loss | C94: Lost Time, Percentage Time Lost to Obstacles | D94: 501b; 501d | E94: 160; 501; 146 | F94: Quantifies the percentage (or hours) of developer time lost each week to obstacles in the work environment (e.g., unclear requirements, excessive meetings, context switching, or technical debt) typically collected via self-reported survey. Often expressed as a cost (translatable into engineering-dollar terms) to make the impact tangible to business stakeholders. | G94: qualitative | H94: Developer Enablement | I94: =VLOOKUP(H94,cardsort_group_IDs!A:B,2,0) -> 203 | J94: Ease of Delivery | K94: =VLOOKUP(J94,cardsort_subgroup_IDs!A:B,2,0) -> 313 | L94: =IF(E94="-",0,1)+IF(D94="-",0,2) -> 3 | M94: =IF(D94="-",0,LEN(D94)-LEN(SUBSTITUTE(D94,";",""))+1) -> 2 | N94: =IF(E94="-",0,LEN(E94)-LEN(SUBSTITUTE(E94,";",""))+1) -> 3 | O94: =SUM(M94:N94) -> 5 | P94: None | Q94: Developer Experience | R94: Moderate | S94: -
A95: 133 | B95: Defect Resolution Time | C95: Bug Resolution Time | D95: - | E95: 96 | F95: Measures the time taken to resolve a reported defect, from identification to fix. | G95: quantitative | H95: Quality | I95: =VLOOKUP(H95,cardsort_group_IDs!A:B,2,0) -> 205 | J95: Code Quality | K95: =VLOOKUP(J95,cardsort_subgroup_IDs!A:B,2,0) -> 319 | L95: =IF(E95="-",0,1)+IF(D95="-",0,2) -> 1 | M95: =IF(D95="-",0,LEN(D95)-LEN(SUBSTITUTE(D95,";",""))+1) -> 0 | N95: =IF(E95="-",0,LEN(E95)-LEN(SUBSTITUTE(E95,";",""))+1) -> 1 | O95: =SUM(M95:N95) -> 1 | P95: Impact | Q95: Product Excellence | R95: Moderate | S95: 26; 29; 42; 70; 134
A96: 134 | B96: Bug Fixing Contribution Percentage | C96: - | D96: - | E96: 21 | F96: Quantifies the percentage of a developer's commits made on bug-fixing tasks, relative to the rest of the team. | G96: quantitative | H96: Quality | I96: =VLOOKUP(H96,cardsort_group_IDs!A:B,2,0) -> 205 | J96: Code Quality | K96: =VLOOKUP(J96,cardsort_subgroup_IDs!A:B,2,0) -> 319 | L96: =IF(E96="-",0,1)+IF(D96="-",0,2) -> 1 | M96: =IF(D96="-",0,LEN(D96)-LEN(SUBSTITUTE(D96,";",""))+1) -> 0 | N96: =IF(E96="-",0,LEN(E96)-LEN(SUBSTITUTE(E96,";",""))+1) -> 1 | O96: =SUM(M96:N96) -> 1 | P96: Impact | Q96: Product Excellence | R96: Easy | S96: 23; 70; 26; 29; 42; 133
A97: 135 | B97: Career Development Opportunities | C97: - | D97: - | E97: 183 | F97: Is a metric that shows the availability of career advancement opportunities. | G97: qualitative | H97: Developer Enablement | I97: =VLOOKUP(H97,cardsort_group_IDs!A:B,2,0) -> 203 | J97: Upskilling | K97: =VLOOKUP(J97,cardsort_subgroup_IDs!A:B,2,0) -> 328 | L97: =IF(E97="-",0,1)+IF(D97="-",0,2) -> 1 | M97: =IF(D97="-",0,LEN(D97)-LEN(SUBSTITUTE(D97,";",""))+1) -> 0 | N97: =IF(E97="-",0,LEN(E97)-LEN(SUBSTITUTE(E97,";",""))+1) -> 1 | O97: =SUM(M97:N97) -> 1 | P97: None | Q97: Developer Experience | R97: Moderate | S97: -
A98: 137 | B98: Complexity | C98: Halstead Effort by Time; Average Complexity per Method; Weighted Methods | D98: - | E98: 7; 15; 21; 51; 52; 92 | F98: Metrics related to complexity of methods or tasks in the coding process. | G98: quantitative | H98: Developer Enablement | I98: =VLOOKUP(H98,cardsort_group_IDs!A:B,2,0) -> 203 | J98: Ease of Delivery | K98: =VLOOKUP(J98,cardsort_subgroup_IDs!A:B,2,0) -> 313 | L98: =IF(E98="-",0,1)+IF(D98="-",0,2) -> 1 | M98: =IF(D98="-",0,LEN(D98)-LEN(SUBSTITUTE(D98,";",""))+1) -> 0 | N98: =IF(E98="-",0,LEN(E98)-LEN(SUBSTITUTE(E98,";",""))+1) -> 6 | O98: =SUM(M98:N98) -> 6 | P98: None | Q98: Product Excellence | R98: Moderate | S98: -
A99: 138 | B99: Cost per Function Point | C99: Investment in Progress; Cost per FP | D99: - | E99: 236 | F99: Metrics related to cost or investments. | G99: quantitative | H99: Business | I99: =VLOOKUP(H99,cardsort_group_IDs!A:B,2,0) -> 201 | J99: Optimal Resource Allocation | K99: =VLOOKUP(J99,cardsort_subgroup_IDs!A:B,2,0) -> 302 | L99: =IF(E99="-",0,1)+IF(D99="-",0,2) -> 1 | M99: =IF(D99="-",0,LEN(D99)-LEN(SUBSTITUTE(D99,";",""))+1) -> 0 | N99: =IF(E99="-",0,LEN(E99)-LEN(SUBSTITUTE(E99,";",""))+1) -> 1 | O99: =SUM(M99:N99) -> 1 | P99: None | Q99: Organizational Effectiveness | R99: Easy | S99: -
A100: 139 | B100: Test Failure Rate | C100: - | D100: 510 | E100: - | F100: A metric used to measure the percentage of test cases that fail during a specific testing period or for a particular software build. | G100: quantitative | H100: System | I100: =VLOOKUP(H100,cardsort_group_IDs!A:B,2,0) -> 202 | J100: Reliability and Stability | K100: =VLOOKUP(J100,cardsort_subgroup_IDs!A:B,2,0) -> 304 | L100: =IF(E100="-",0,1)+IF(D100="-",0,2) -> 2 | M100: =IF(D100="-",0,LEN(D100)-LEN(SUBSTITUTE(D100,";",""))+1) -> 1 | N100: =IF(E100="-",0,LEN(E100)-LEN(SUBSTITUTE(E100,";",""))+1) -> 0 | O100: =SUM(M100:N100) -> 1 | P100: None | Q100: Product Excellence | R100: Easy | S100: -
...

Sheet urls
A1: ref_number | B1: ref_name | C1: company_size | D1: ref_link
A2: 5 | B2: D’Angelo et al. (2024) | C2: N/A | D2: https://doi.org/10.1109/MS.2024.3386027
A3: 6 | B3: Brown et al. (2023) | C3: N/A | D3: https://doi.org/10.1109/MS.2023.3305718
A4: 6a | B4: Google | C4: Enterprise | D4: https://doi.org/10.1109/MS.2023.3305718
A5: 7 | B5: Oliveira et al. (2020) | C5: N/A | D5: https://doi.org/10.1007/s10664-020-09820-z
A6: 9 | B6: Sanwal and Deva (2024) | C6: N/A | D6: https://www.ijtsrd.com/papers/ijtsrd69393.pdf
A7: 11 | B7: Gonçales et al. (2019) | C7: N/A | D7: https://doi.org/10.1109/ICPC.2019.00018
A8: 13 | B8: Edberg and Bowman (2015) | C8: N/A | D8: https://doi.org/10.1080/07421222.1996.11518117
A9: 14 | B9: Kokrehel and Bilicki (2021) | C9: N/A | D9: https://doi.org/10.1556/606.2021.00372
A10: 15 | B10: Oliveira et al. (2017) | C10: N/A | D10: https://doi.org/10.5220/0006314400760087
A11: 17 | B11: Green et al. (2024) | C11: N/A | D11: https://doi.org/10.1109/MS.2023.3324830
A12: 19 | B12: Meyer et al. (2014) | C12: N/A | D12: https://doi.org/10.1145/2635868.2635892
A13: 20 | B13: Green et al. (2023) | C13: N/A | D13: https://doi.org/10.1109/MS.2023.3291158
A14: 21 | B14: Treude et al. (2015) | C14: N/A | D14: https://doi.org/10.1145/2786805.2786827
A15: 31 | B15: Bao et al. (2022) | C15: N/A | D15: https://doi.org/10.1007/s11432-020-3278-4
A16: 32 | B16: Cheng et al. (2022) | C16: N/A | D16: https://doi.org/10.1145/3540250.3558940
... A70: 510 | B70: Slack | C70: Enterprise | D70: https://slack.engineering/mobile-developer-experience-at-slack/
A71: 131a | B71: Dropbox | C71: Large | D71: https://www.gitpod.io/blog/20-most-popular-developer-productivity-metrics
A72: 131b | B72: Netflix | C72: Enterprise | D72: https://www.gitpod.io/blog/20-most-popular-developer-productivity-metrics
A73: 131c | B73: Twitter/X | C73: Large | D73: https://www.gitpod.io/blog/20-most-popular-developer-productivity-metrics
A74: 131d | B74: Mozilla | C74: Mid-size | D74: https://www.gitpod.io/blog/20-most-popular-developer-productivity-metrics
A75: 131e | B75: Atlassian | C75: Enterprise | D75: https://www.gitpod.io/blog/20-most-popular-developer-productivity-metrics
A76: 131f | B76: SonarSource | C76: Mid-size | D76: https://www.gitpod.io/blog/20-most-popular-developer-productivity-metrics
A77: 131g | B77: Square | C77: Enterprise | D77: https://www.gitpod.io/blog/20-most-popular-developer-productivity-metrics
A78: 131h | B78: Etsy | C78: Large | D78: https://www.gitpod.io/blog/20-most-popular-developer-productivity-metrics
A79: 131i | B79: Stripe | C79: Enterprise | D79: https://www.gitpod.io/blog/20-most-popular-developer-productivity-metrics
A80: 131j | B80: Microsoft | C80: Enterprise | D80: https://www.gitpod.io/blog/20-most-popular-developer-productivity-metrics
A81: 131k | B81: Amazon | C81: Enterprise | D81: https://www.gitpod.io/blog/20-most-popular-developer-productivity-metrics
A82: 131l | B82: Meta | C82: Enterprise | D82: https://www.gitpod.io/blog/20-most-popular-developer-productivity-metrics
... A153: 523 | B153: Brandebusemeyer (2026) | C153: N/A | D153: https://dl.acm.org/doi/10.1145/3847122
A154: 524a | B154: SonarSource | C154: N/A | D154: https://www.sonarsource.com/resources/library/measuring-and-identifying-code-level-technical-debt-a-practical-guide/ | E154: Reference-for-Implementation
A155: 524b | B155: DX (2025) | C155: N/A | D155: https://getdx.com/blog/technical-debt-ratio/ | E155: Reference-for-Implementation
A156: 525a | B156: Storey (2026) | C156: N/A | D156: https://arxiv.org/abs/2603.22106
A157: 525b | B157: Alakmeh (2026) | C157: N/A | D157: https://dl.acm.org/doi/10.1145/3794763.3794804

Sheet cardsort_group_IDs
A1: Business | B1: 201
A2: System | B2: 202
A3: Developer Enablement | B3: 203
A4: Process | B4: 204
A5: Quality | B5: 205
A6: Team | B6: 206
A7: Output | B7: 207
A8: Customer | B8: 208

Sheet cardsort_subgroup_IDs
A1: Operational Flexibility | B1: 301
A2: Optimal Resource Allocation | B2: 302
A3: Build Time | B3: 303
A4: Reliability and Stability | B4: 304
A5: Focus Work | B5: 305
A6: Cycle Time | B6: 306
A7: Work Load | B7: 307
A8: Failure Rate | B8: 308
A9: Test Coverage | B9: 309
A10: Code Rework | B10: 310
A11: Review Process | B11: 311
A12: Produced Output | B12: 312
... A32: AI-Assisted Output | B32: 333

Sheet company_sizes
A1: company_size | B1: developer_count
A2: Enterprise | B2: 5000+ developers
A3: Large | B3: 501-5000
A4: Mid-size | B4: 51-500
A5: Small | B5: 1-50
A6: N/A | B6: research_instituation
